{
  "19021": {
    "value": 2.4,
    "rank": 15
  },
  "19051": {
    "value": 2.5,
    "rank": 14
  },
  "19076": {
    "value": 2.8,
    "rank": 13
  },
  "19151": {
    "value": 3.3,
    "rank": 4
  },
  "19191": {
    "value": 3.3,
    "rank": 4
  },
  "19261": {
    "value": 3.4,
    "rank": 1
  },
  "19281": {
    "value": 3.1,
    "rank": 9
  },
  "19301": {
    "value": 3.4,
    "rank": 1
  },
  "19311": {
    "value": 3.3,
    "rank": 4
  },
  "19346": {
    "value": 3.4,
    "rank": 1
  },
  "19376": {
    "value": 3.3,
    "rank": 4
  },
  "19406": {
    "value": 3,
    "rank": 12
  },
  "19416": {
    "value": 3.1,
    "rank": 9
  },
  "19432": {
    "value": 3.3,
    "rank": 4
  },
  "19451": {
    "value": 3.1,
    "rank": 9
  }
}