{"hitemp_0":[{"value":0.9,"top":390,"region":133,"pre":31,"bot":511,"island":390},{"value":0.6,"top":395,"region":132,"pre":31,"bot":494,"island":395},{"value":0,"top":904,"region":153,"pre":33,"bot":1,"island":856},{"value":0,"top":904,"region":153,"pre":33,"bot":1,"island":856},{"value":0,"top":904,"region":153,"pre":33,"bot":1,"island":856},{"value":0,"top":904,"region":153,"pre":33,"bot":1,"island":856},{"value":0,"top":904,"region":153,"pre":33,"bot":1,"island":856},{"value":0,"top":904,"region":153,"pre":33,"bot":1,"island":856},{"value":0,"top":904,"region":153,"pre":33,"bot":1,"island":856},{"value":0,"top":904,"region":153,"pre":33,"bot":1,"island":856},{"value":0,"top":904,"region":153,"pre":33,"bot":1,"island":856},{"value":0.2,"top":386,"region":130,"pre":31,"bot":503,"island":386},{"value":1.8,"top":390,"region":133,"pre":31,"bot":514,"island":390}],"hitemp_25":[{"value":0,"top":904,"region":153,"pre":33,"bot":1,"island":856},{"value":0,"top":904,"region":153,"pre":33,"bot":1,"island":856},{"value":0,"top":904,"region":153,"pre":33,"bot":1,"island":856},{"value":0.8,"top":466,"region":35,"pre":4,"bot":404,"island":427},{"value":4.1,"top":594,"region":78,"pre":14,"bot":307,"island":554},{"value":7.3,"top":693,"region":108,"pre":23,"bot":211,"island":646},{"value":16.5,"top":714,"region":122,"pre":24,"bot":188,"island":666},{"value":22.1,"top":685,"region":118,"pre":20,"bot":220,"island":637},{"value":12.2,"top":638,"region":87,"pre":12,"bot":264,"island":590},{"value":1.2,"top":561,"region":27,"pre":1,"bot":334,"island":513},{"value":0,"top":904,"region":153,"pre":33,"bot":1,"island":856},{"value":0,"top":904,"region":153,"pre":33,"bot":1,"island":856},{"value":64.6,"top":672,"region":107,"pre":19,"bot":233,"island":624}],"hitemp_30":[{"value":0,"top":904,"region":153,"pre":33,"bot":1,"island":856},{"value":0,"top":904,"region":153,"pre":33,"bot":1,"island":856},{"value":0,"top":904,"region":153,"pre":33,"bot":1,"island":856},{"value":0.1,"top":57,"region":3,"pre":1,"bot":714,"island":47},{"value":0.4,"top":359,"region":33,"pre":8,"bot":492,"island":333},{"value":1.3,"top":482,"region":48,"pre":11,"bot":409,"island":444},{"value":6.1,"top":615,"region":76,"pre":15,"bot":288,"island":571},{"value":9.7,"top":634,"region":86,"pre":15,"bot":267,"island":588},{"value":2.5,"top":568,"region":54,"pre":5,"bot":329,"island":523},{"value":0,"top":904,"region":153,"pre":33,"bot":1,"island":856},{"value":0,"top":904,"region":153,"pre":33,"bot":1,"island":856},{"value":0,"top":904,"region":153,"pre":33,"bot":1,"island":856},{"value":20.6,"top":616,"region":78,"pre":14,"bot":289,"island":570}],"hitemp_35":[{"value":0,"top":904,"region":153,"pre":33,"bot":1,"island":856},{"value":0,"top":904,"region":153,"pre":33,"bot":1,"island":856},{"value":0,"top":904,"region":153,"pre":33,"bot":1,"island":856},{"value":0,"top":904,"region":153,"pre":33,"bot":1,"island":856},{"value":0,"top":904,"region":153,"pre":33,"bot":1,"island":856},{"value":0,"top":904,"region":153,"pre":33,"bot":1,"island":856},{"value":0.6,"top":321,"region":15,"pre":2,"bot":549,"island":320},{"value":1.2,"top":370,"region":27,"pre":4,"bot":524,"island":370},{"value":0.1,"top":269,"region":16,"pre":1,"bot":499,"island":269},{"value":0,"top":904,"region":153,"pre":33,"bot":1,"island":856},{"value":0,"top":904,"region":153,"pre":33,"bot":1,"island":856},{"value":0,"top":904,"region":153,"pre":33,"bot":1,"island":856},{"value":2,"top":349,"region":17,"pre":2,"bot":542,"island":349}],"lwtemp_0":[{"value":26.7,"top":399,"region":127,"pre":32,"bot":506,"island":399},{"value":23.6,"top":393,"region":129,"pre":33,"bot":511,"island":393},{"value":17,"top":385,"region":126,"pre":32,"bot":517,"island":385},{"value":2,"top":441,"region":133,"pre":33,"bot":458,"island":441},{"value":0,"top":904,"region":153,"pre":33,"bot":1,"island":856},{"value":0,"top":904,"region":153,"pre":33,"bot":1,"island":856},{"value":0,"top":904,"region":153,"pre":33,"bot":1,"island":856},{"value":0,"top":904,"region":153,"pre":33,"bot":1,"island":856},{"value":0,"top":904,"region":153,"pre":33,"bot":1,"island":856},{"value":0,"top":904,"region":153,"pre":33,"bot":1,"island":856},{"value":3.6,"top":401,"region":125,"pre":32,"bot":504,"island":401},{"value":18.1,"top":419,"region":129,"pre":32,"bot":483,"island":419},{"value":90.1,"top":408,"region":129,"pre":32,"bot":497,"island":408}],"lwtemp_25":[{"value":0,"top":904,"region":153,"pre":33,"bot":1,"island":856},{"value":0,"top":904,"region":153,"pre":33,"bot":1,"island":856},{"value":0,"top":904,"region":153,"pre":33,"bot":1,"island":856},{"value":0,"top":904,"region":153,"pre":33,"bot":1,"island":856},{"value":0,"top":904,"region":153,"pre":33,"bot":1,"island":856},{"value":0,"top":904,"region":153,"pre":33,"bot":1,"island":856},{"value":0,"top":904,"region":153,"pre":33,"bot":1,"island":856},{"value":0.3,"top":469,"region":29,"pre":2,"bot":418,"island":421},{"value":0.1,"top":380,"region":19,"pre":4,"bot":462,"island":332},{"value":0,"top":904,"region":153,"pre":33,"bot":1,"island":856},{"value":0,"top":904,"region":153,"pre":33,"bot":1,"island":856},{"value":0,"top":904,"region":153,"pre":33,"bot":1,"island":856},{"value":0.4,"top":476,"region":34,"pre":3,"bot":410,"island":428}],"rain_1":[{"value":5.4,"top":1025,"region":174,"pre":37,"bot":182},{"value":5.9,"top":1058,"region":164,"pre":36,"bot":158},{"value":8.4,"top":1100,"region":171,"pre":36,"bot":122},{"value":9.1,"top":1038,"region":159,"pre":34,"bot":175},{"value":9.7,"top":882,"region":150,"pre":37,"bot":308},{"value":10.4,"top":906,"region":111,"pre":15,"bot":318},{"value":12.6,"top":517,"region":138,"pre":29,"bot":687},{"value":11.4,"top":468,"region":118,"pre":30,"bot":735},{"value":11.9,"top":508,"region":103,"pre":15,"bot":687},{"value":9.2,"top":839,"region":168,"pre":36,"bot":372},{"value":6.9,"top":1015,"region":168,"pre":37,"bot":195},{"value":5.9,"top":1032,"region":177,"pre":39,"bot":181},{"value":106.9,"top":1016,"region":175,"pre":37,"bot":211}],"rain_10":[{"value":1.7,"top":810,"region":113,"pre":10,"bot":373},{"value":1.5,"top":911,"region":118,"pre":15,"bot":294},{"value":2.8,"top":867,"region":87,"pre":8,"bot":344},{"value":3.2,"top":828,"region":89,"pre":13,"bot":380},{"value":3.5,"top":891,"region":95,"pre":18,"bot":310},{"value":4.4,"top":773,"region":42,"pre":7,"bot":423},{"value":4.6,"top":895,"region":162,"pre":39,"bot":321},{"value":5,"top":457,"region":91,"pre":18,"bot":732},{"value":5.3,"top":543,"region":55,"pre":5,"bot":644},{"value":4.3,"top":556,"region":84,"pre":6,"bot":630},{"value":2.3,"top":991,"region":133,"pre":21,"bot":188},{"value":1.7,"top":978,"region":133,"pre":23,"bot":213},{"value":40.5,"top":879,"region":109,"pre":11,"bot":349}],"rain_100":[{"value":0.1,"top":8,"region":1,"pre":1,"bot":1165},{"value":0,"top":1230,"region":197,"pre":44,"bot":1},{"value":0,"top":1230,"region":197,"pre":44,"bot":1},{"value":0.1,"top":121,"region":3,"pre":1,"bot":933},{"value":0.3,"top":77,"region":1,"pre":1,"bot":1092},{"value":0.3,"top":224,"region":1,"pre":1,"bot":940},{"value":0.2,"top":431,"region":14,"pre":2,"bot":614},{"value":0.2,"top":334,"region":15,"pre":2,"bot":680},{"value":0.6,"top":98,"region":1,"pre":1,"bot":1081},{"value":0.4,"top":98,"region":11,"pre":3,"bot":1058},{"value":0.1,"top":80,"region":1,"pre":1,"bot":996},{"value":0.1,"top":16,"region":1,"pre":1,"bot":1072},{"value":2.5,"top":193,"region":1,"pre":1,"bot":1025}],"rain_30":[{"value":0.5,"top":334,"region":31,"pre":5,"bot":781},{"value":0.4,"top":420,"region":16,"pre":4,"bot":723},{"value":1.3,"top":216,"region":1,"pre":1,"bot":973},{"value":1.2,"top":371,"region":6,"pre":2,"bot":813},{"value":1.3,"top":493,"region":12,"pre":4,"bot":689},{"value":1.8,"top":497,"region":9,"pre":4,"bot":688},{"value":1.4,"top":912,"region":152,"pre":35,"bot":275},{"value":2.3,"top":235,"region":25,"pre":4,"bot":952},{"value":2.4,"top":313,"region":7,"pre":1,"bot":871},{"value":2,"top":206,"region":7,"pre":1,"bot":989},{"value":0.9,"top":357,"region":41,"pre":4,"bot":819},{"value":0.5,"top":449,"region":55,"pre":6,"bot":683},{"value":16.3,"top":456,"region":20,"pre":3,"bot":768}],"rain_50":[{"value":0.3,"top":72,"region":2,"pre":2,"bot":1088},{"value":0.1,"top":257,"region":8,"pre":5,"bot":718},{"value":0.5,"top":138,"region":1,"pre":1,"bot":1052},{"value":0.6,"top":208,"region":1,"pre":1,"bot":971},{"value":0.7,"top":299,"region":2,"pre":2,"bot":889},{"value":0.7,"top":485,"region":10,"pre":5,"bot":676},{"value":0.8,"top":627,"region":56,"pre":9,"bot":519},{"value":1.2,"top":204,"region":16,"pre":3,"bot":978},{"value":1.4,"top":210,"region":3,"pre":2,"bot":978},{"value":1.3,"top":87,"region":2,"pre":1,"bot":1120},{"value":0.4,"top":198,"region":6,"pre":1,"bot":957},{"value":0.3,"top":147,"region":9,"pre":2,"bot":987},{"value":8.5,"top":290,"region":1,"pre":1,"bot":932}],"rain_70":[{"value":0.2,"top":24,"region":3,"pre":3,"bot":1164},{"value":0.1,"top":83,"region":1,"pre":1,"bot":1011},{"value":0.2,"top":102,"region":2,"pre":2,"bot":1056},{"value":0.3,"top":162,"region":1,"pre":1,"bot":991},{"value":0.5,"top":164,"region":1,"pre":1,"bot":1012},{"value":0.5,"top":331,"region":2,"pre":1,"bot":851},{"value":0.5,"top":476,"region":22,"pre":2,"bot":654},{"value":0.7,"top":189,"region":8,"pre":2,"bot":978},{"value":1,"top":133,"region":1,"pre":1,"bot":1067},{"value":0.7,"top":127,"region":11,"pre":3,"bot":1045},{"value":0.2,"top":140,"region":2,"pre":1,"bot":990},{"value":0.2,"top":52,"region":2,"pre":1,"bot":1103},{"value":5.2,"top":211,"region":1,"pre":1,"bot":1015}],"snowed_10":[{},{},{},{},{},{},{},{},{},{},{},{},{}],"snowed_100":[{},{},{},{},{},{},{},{},{},{},{},{},{}],"snowed_20":[{},{},{},{},{},{},{},{},{},{},{},{},{}],"snowed_5":[{},{},{},{},{},{},{},{},{},{},{},{},{}],"snowed_50":[{},{},{},{},{},{},{},{},{},{},{},{},{}],"snowing_10":[{},{},{},{},{},{},{},{},{},{},{},{},{}],"snowing_20":[{},{},{},{},{},{},{},{},{},{},{},{},{}],"snowing_3":[{},{},{},{},{},{},{},{},{},{},{},{},{}],"snowing_5":[{},{},{},{},{},{},{},{},{},{},{},{},{}],"snowing_50":[{},{},{},{},{},{},{},{},{},{},{},{},{}],"wind_10":[{"value":0.4,"top":454,"region":76,"pre":14,"bot":398},{"value":0.8,"top":394,"region":67,"pre":12,"bot":466},{"value":0.7,"top":449,"region":77,"pre":14,"bot":399},{"value":0.3,"top":553,"region":94,"pre":19,"bot":278},{"value":0.2,"top":478,"region":81,"pre":15,"bot":333},{"value":0.1,"top":419,"region":55,"pre":6,"bot":310},{"value":0,"top":874,"region":134,"pre":32,"bot":1},{"value":0.1,"top":495,"region":54,"pre":8,"bot":230},{"value":0.1,"top":644,"region":83,"pre":13,"bot":116},{"value":0.1,"top":582,"region":87,"pre":20,"bot":174},{"value":0.2,"top":469,"region":82,"pre":16,"bot":364},{"value":0.6,"top":432,"region":76,"pre":13,"bot":431},{"value":3.7,"top":503,"region":81,"pre":16,"bot":368}],"wind_15":[{"value":0,"top":874,"region":134,"pre":32,"bot":1},{"value":0,"top":874,"region":134,"pre":32,"bot":1},{"value":0.1,"top":210,"region":33,"pre":3,"bot":586},{"value":0,"top":874,"region":134,"pre":32,"bot":1},{"value":0,"top":874,"region":134,"pre":32,"bot":1},{"value":0,"top":874,"region":134,"pre":32,"bot":1},{"value":0,"top":874,"region":134,"pre":32,"bot":1},{"value":0,"top":874,"region":134,"pre":32,"bot":1},{"value":0,"top":874,"region":134,"pre":32,"bot":1},{"value":0,"top":874,"region":134,"pre":32,"bot":1},{"value":0,"top":874,"region":134,"pre":32,"bot":1},{"value":0,"top":874,"region":134,"pre":32,"bot":1},{"value":0.1,"top":472,"region":62,"pre":11,"bot":303}],"wind_20":[{"value":0,"top":874,"region":134,"pre":32,"bot":1},{"value":0,"top":874,"region":134,"pre":32,"bot":1},{"value":0,"top":874,"region":134,"pre":32,"bot":1},{"value":0,"top":874,"region":134,"pre":32,"bot":1},{"value":0,"top":874,"region":134,"pre":32,"bot":1},{"value":0,"top":874,"region":134,"pre":32,"bot":1},{"value":0,"top":874,"region":134,"pre":32,"bot":1},{"value":0,"top":874,"region":134,"pre":32,"bot":1},{"value":0,"top":874,"region":134,"pre":32,"bot":1},{"value":0,"top":874,"region":134,"pre":32,"bot":1},{"value":0,"top":874,"region":134,"pre":32,"bot":1},{"value":0,"top":874,"region":134,"pre":32,"bot":1},{"value":0,"top":874,"region":134,"pre":32,"bot":1}],"wind_30":[{"value":0,"top":874,"region":134,"pre":32,"bot":1},{"value":0,"top":874,"region":134,"pre":32,"bot":1},{"value":0,"top":874,"region":134,"pre":32,"bot":1},{"value":0,"top":874,"region":134,"pre":32,"bot":1},{"value":0,"top":874,"region":134,"pre":32,"bot":1},{"value":0,"top":874,"region":134,"pre":32,"bot":1},{"value":0,"top":874,"region":134,"pre":32,"bot":1},{"value":0,"top":874,"region":134,"pre":32,"bot":1},{"value":0,"top":874,"region":134,"pre":32,"bot":1},{"value":0,"top":874,"region":134,"pre":32,"bot":1},{"value":0,"top":874,"region":134,"pre":32,"bot":1},{"value":0,"top":874,"region":134,"pre":32,"bot":1},{"value":0,"top":874,"region":134,"pre":32,"bot":1}]}