{
  "number": "66127",
  "station_name": "奈義",
  "kana_name": "ﾅｷﾞ",
  "lon": 35.112,
  "lat": 134.17,
  "height": 212,
  "official_name": "奈義アメダス",
  "pref": "岡山県",
  "city": "勝田郡奈義町",
  "data": {
    "av_avtemp": {
      "1": {
        "value": 1.8,
        "rank": {
          "top": 467,
          "region": 63,
          "pre": 12,
          "bot": 430,
          "island": 419
        }
      },
      "2": {
        "value": 2.6,
        "rank": {
          "top": 456,
          "region": 64,
          "pre": 12,
          "bot": 443,
          "island": 408
        }
      },
      "3": {
        "value": 6.1,
        "rank": {
          "top": 447,
          "region": 64,
          "pre": 12,
          "bot": 454,
          "island": 399
        }
      },
      "4": {
        "value": 11.6,
        "rank": {
          "top": 438,
          "region": 63,
          "pre": 12,
          "bot": 462,
          "island": 390
        }
      },
      "5": {
        "value": 17.0,
        "rank": {
          "top": 405,
          "region": 54,
          "pre": 12,
          "bot": 489,
          "island": 357
        }
      },
      "6": {
        "value": 21.0,
        "rank": {
          "top": 369,
          "region": 49,
          "pre": 12,
          "bot": 520,
          "island": 322
        }
      },
      "7": {
        "value": 24.8,
        "rank": {
          "top": 379,
          "region": 54,
          "pre": 12,
          "bot": 513,
          "island": 333
        }
      },
      "8": {
        "value": 25.7,
        "rank": {
          "top": 409,
          "region": 58,
          "pre": 12,
          "bot": 487,
          "island": 361
        }
      },
      "9": {
        "value": 21.6,
        "rank": {
          "top": 442,
          "region": 57,
          "pre": 12,
          "bot": 456,
          "island": 394
        }
      },
      "10": {
        "value": 15.3,
        "rank": {
          "top": 471,
          "region": 59,
          "pre": 12,
          "bot": 429,
          "island": 423
        }
      },
      "11": {
        "value": 9.1,
        "rank": {
          "top": 490,
          "region": 64,
          "pre": 12,
          "bot": 411,
          "island": 442
        }
      },
      "12": {
        "value": 3.8,
        "rank": {
          "top": 487,
          "region": 65,
          "pre": 12,
          "bot": 411,
          "island": 439
        }
      },
      "all": {
        "value": 13.4,
        "rank": {
          "top": 442,
          "region": 60,
          "pre": 12,
          "bot": 452,
          "island": 394
        }
      }
    },
    "av_hitemp": {
      "1": {
        "value": 6.8,
        "rank": {
          "top": 437,
          "region": 60,
          "pre": 12,
          "bot": 462,
          "island": 389
        }
      },
      "2": {
        "value": 7.9,
        "rank": {
          "top": 437,
          "region": 63,
          "pre": 12,
          "bot": 464,
          "island": 389
        }
      },
      "3": {
        "value": 12.1,
        "rank": {
          "top": 421,
          "region": 61,
          "pre": 12,
          "bot": 478,
          "island": 373
        }
      },
      "4": {
        "value": 18.3,
        "rank": {
          "top": 355,
          "region": 42,
          "pre": 12,
          "bot": 545,
          "island": 310
        }
      },
      "5": {
        "value": 23.2,
        "rank": {
          "top": 307,
          "region": 36,
          "pre": 11,
          "bot": 582,
          "island": 268
        }
      },
      "6": {
        "value": 26.2,
        "rank": {
          "top": 257,
          "region": 32,
          "pre": 11,
          "bot": 635,
          "island": 220
        }
      },
      "7": {
        "value": 29.7,
        "rank": {
          "top": 306,
          "region": 40,
          "pre": 12,
          "bot": 586,
          "island": 269
        }
      },
      "8": {
        "value": 31.2,
        "rank": {
          "top": 299,
          "region": 44,
          "pre": 13,
          "bot": 592,
          "island": 271
        }
      },
      "9": {
        "value": 27.0,
        "rank": {
          "top": 370,
          "region": 46,
          "pre": 13,
          "bot": 522,
          "island": 326
        }
      },
      "10": {
        "value": 21.3,
        "rank": {
          "top": 411,
          "region": 58,
          "pre": 13,
          "bot": 482,
          "island": 363
        }
      },
      "11": {
        "value": 15.2,
        "rank": {
          "top": 447,
          "region": 63,
          "pre": 12,
          "bot": 450,
          "island": 399
        }
      },
      "12": {
        "value": 9.2,
        "rank": {
          "top": 456,
          "region": 60,
          "pre": 12,
          "bot": 445,
          "island": 408
        }
      },
      "all": {
        "value": 19.0,
        "rank": {
          "top": 407,
          "region": 56,
          "pre": 13,
          "bot": 489,
          "island": 359
        }
      }
    },
    "av_lwtemp": {
      "1": {
        "value": -2.7,
        "rank": {
          "top": 499,
          "region": 68,
          "pre": 13,
          "bot": 401,
          "island": 451
        }
      },
      "2": {
        "value": -2.4,
        "rank": {
          "top": 500,
          "region": 66,
          "pre": 13,
          "bot": 401,
          "island": 452
        }
      },
      "3": {
        "value": 0.3,
        "rank": {
          "top": 499,
          "region": 66,
          "pre": 13,
          "bot": 404,
          "island": 451
        }
      },
      "4": {
        "value": 4.8,
        "rank": {
          "top": 512,
          "region": 67,
          "pre": 13,
          "bot": 391,
          "island": 464
        }
      },
      "5": {
        "value": 11.0,
        "rank": {
          "top": 467,
          "region": 56,
          "pre": 10,
          "bot": 427,
          "island": 419
        }
      },
      "6": {
        "value": 16.6,
        "rank": {
          "top": 418,
          "region": 53,
          "pre": 10,
          "bot": 477,
          "island": 370
        }
      },
      "7": {
        "value": 21.1,
        "rank": {
          "top": 403,
          "region": 55,
          "pre": 12,
          "bot": 487,
          "island": 355
        }
      },
      "8": {
        "value": 21.5,
        "rank": {
          "top": 447,
          "region": 59,
          "pre": 12,
          "bot": 451,
          "island": 399
        }
      },
      "9": {
        "value": 17.0,
        "rank": {
          "top": 490,
          "region": 61,
          "pre": 12,
          "bot": 410,
          "island": 442
        }
      },
      "10": {
        "value": 9.9,
        "rank": {
          "top": 527,
          "region": 65,
          "pre": 13,
          "bot": 371,
          "island": 479
        }
      },
      "11": {
        "value": 3.7,
        "rank": {
          "top": 528,
          "region": 65,
          "pre": 13,
          "bot": 374,
          "island": 480
        }
      },
      "12": {
        "value": -0.9,
        "rank": {
          "top": 527,
          "region": 70,
          "pre": 14,
          "bot": 371,
          "island": 479
        }
      },
      "all": {
        "value": 8.3,
        "rank": {
          "top": 490,
          "region": 65,
          "pre": 12,
          "bot": 409,
          "island": 442
        }
      }
    },
    "av_wind": {
      "1": {
        "value": 1.4,
        "rank": {
          "top": 710,
          "region": 53,
          "pre": 8,
          "bot": 142
        }
      },
      "2": {
        "value": 1.5,
        "rank": {
          "top": 712,
          "region": 53,
          "pre": 8,
          "bot": 133
        }
      },
      "3": {
        "value": 1.7,
        "rank": {
          "top": 700,
          "region": 50,
          "pre": 7,
          "bot": 150
        }
      },
      "4": {
        "value": 1.7,
        "rank": {
          "top": 707,
          "region": 52,
          "pre": 7,
          "bot": 141
        }
      },
      "5": {
        "value": 1.5,
        "rank": {
          "top": 711,
          "region": 55,
          "pre": 7,
          "bot": 128
        }
      },
      "6": {
        "value": 1.3,
        "rank": {
          "top": 697,
          "region": 55,
          "pre": 8,
          "bot": 141
        }
      },
      "7": {
        "value": 1.2,
        "rank": {
          "top": 714,
          "region": 63,
          "pre": 9,
          "bot": 125
        }
      },
      "8": {
        "value": 1.3,
        "rank": {
          "top": 675,
          "region": 56,
          "pre": 7,
          "bot": 165
        }
      },
      "9": {
        "value": 1.4,
        "rank": {
          "top": 622,
          "region": 51,
          "pre": 7,
          "bot": 213
        }
      },
      "10": {
        "value": 1.4,
        "rank": {
          "top": 635,
          "region": 49,
          "pre": 6,
          "bot": 201
        }
      },
      "11": {
        "value": 1.2,
        "rank": {
          "top": 713,
          "region": 52,
          "pre": 7,
          "bot": 121
        }
      },
      "12": {
        "value": 1.3,
        "rank": {
          "top": 725,
          "region": 54,
          "pre": 8,
          "bot": 123
        }
      },
      "all": {
        "value": 1.4,
        "rank": {
          "top": 706,
          "region": 52,
          "pre": 7,
          "bot": 140
        }
      }
    },
    "hitemp_0": {
      "1": {
        "value": 0.1,
        "rank": {
          "top": 483,
          "region": 32,
          "pre": 7,
          "bot": 347,
          "island": 483
        }
      },
      "2": {
        "value": 0.2,
        "rank": {
          "top": 453,
          "region": 22,
          "pre": 4,
          "bot": 429,
          "island": 453
        }
      },
      "3": {
        "value": 0.0,
        "rank": {
          "top": 904,
          "region": 80,
          "pre": 16,
          "bot": 1,
          "island": 856
        }
      },
      "4": {
        "value": 0.0,
        "rank": {
          "top": 904,
          "region": 80,
          "pre": 16,
          "bot": 1,
          "island": 856
        }
      },
      "5": {
        "value": 0.0,
        "rank": {
          "top": 904,
          "region": 80,
          "pre": 16,
          "bot": 1,
          "island": 856
        }
      },
      "6": {
        "value": 0.0,
        "rank": {
          "top": 904,
          "region": 80,
          "pre": 16,
          "bot": 1,
          "island": 856
        }
      },
      "7": {
        "value": 0.0,
        "rank": {
          "top": 904,
          "region": 80,
          "pre": 16,
          "bot": 1,
          "island": 856
        }
      },
      "8": {
        "value": 0.0,
        "rank": {
          "top": 904,
          "region": 80,
          "pre": 16,
          "bot": 1,
          "island": 856
        }
      },
      "9": {
        "value": 0.0,
        "rank": {
          "top": 904,
          "region": 80,
          "pre": 16,
          "bot": 1,
          "island": 856
        }
      },
      "10": {
        "value": 0.0,
        "rank": {
          "top": 904,
          "region": 80,
          "pre": 16,
          "bot": 1,
          "island": 856
        }
      },
      "11": {
        "value": 0.0,
        "rank": {
          "top": 904,
          "region": 80,
          "pre": 16,
          "bot": 1,
          "island": 856
        }
      },
      "12": {
        "value": 0.1,
        "rank": {
          "top": 403,
          "region": 18,
          "pre": 4,
          "bot": 472,
          "island": 403
        }
      },
      "all": {
        "value": 0.4,
        "rank": {
          "top": 466,
          "region": 27,
          "pre": 5,
          "bot": 432,
          "island": 466
        }
      }
    },
    "hitemp_25": {
      "1": {
        "value": 0.0,
        "rank": {
          "top": 904,
          "region": 80,
          "pre": 16,
          "bot": 1,
          "island": 856
        }
      },
      "2": {
        "value": 0.0,
        "rank": {
          "top": 904,
          "region": 80,
          "pre": 16,
          "bot": 1,
          "island": 856
        }
      },
      "3": {
        "value": 0.0,
        "rank": {
          "top": 904,
          "region": 80,
          "pre": 16,
          "bot": 1,
          "island": 856
        }
      },
      "4": {
        "value": 1.7,
        "rank": {
          "top": 263,
          "region": 31,
          "pre": 10,
          "bot": 628,
          "island": 227
        }
      },
      "5": {
        "value": 10.8,
        "rank": {
          "top": 280,
          "region": 35,
          "pre": 10,
          "bot": 622,
          "island": 243
        }
      },
      "6": {
        "value": 19.9,
        "rank": {
          "top": 269,
          "region": 34,
          "pre": 11,
          "bot": 629,
          "island": 230
        }
      },
      "7": {
        "value": 27.8,
        "rank": {
          "top": 309,
          "region": 40,
          "pre": 11,
          "bot": 588,
          "island": 266
        }
      },
      "8": {
        "value": 30.4,
        "rank": {
          "top": 264,
          "region": 36,
          "pre": 12,
          "bot": 622,
          "island": 222
        }
      },
      "9": {
        "value": 21.7,
        "rank": {
          "top": 362,
          "region": 48,
          "pre": 13,
          "bot": 540,
          "island": 316
        }
      },
      "10": {
        "value": 4.4,
        "rank": {
          "top": 379,
          "region": 46,
          "pre": 13,
          "bot": 522,
          "island": 332
        }
      },
      "11": {
        "value": 0.0,
        "rank": {
          "top": 904,
          "region": 80,
          "pre": 16,
          "bot": 1,
          "island": 856
        }
      },
      "12": {
        "value": 0.0,
        "rank": {
          "top": 904,
          "region": 80,
          "pre": 16,
          "bot": 1,
          "island": 856
        }
      },
      "all": {
        "value": 116.7,
        "rank": {
          "top": 312,
          "region": 41,
          "pre": 13,
          "bot": 592,
          "island": 272
        }
      }
    },
    "hitemp_30": {
      "1": {
        "value": 0.0,
        "rank": {
          "top": 904,
          "region": 80,
          "pre": 16,
          "bot": 1,
          "island": 856
        }
      },
      "2": {
        "value": 0.0,
        "rank": {
          "top": 904,
          "region": 80,
          "pre": 16,
          "bot": 1,
          "island": 856
        }
      },
      "3": {
        "value": 0.0,
        "rank": {
          "top": 904,
          "region": 80,
          "pre": 16,
          "bot": 1,
          "island": 856
        }
      },
      "4": {
        "value": 0.0,
        "rank": {
          "top": 904,
          "region": 80,
          "pre": 16,
          "bot": 1,
          "island": 856
        }
      },
      "5": {
        "value": 0.5,
        "rank": {
          "top": 302,
          "region": 33,
          "pre": 9,
          "bot": 547,
          "island": 278
        }
      },
      "6": {
        "value": 2.9,
        "rank": {
          "top": 293,
          "region": 32,
          "pre": 10,
          "bot": 604,
          "island": 257
        }
      },
      "7": {
        "value": 15.8,
        "rank": {
          "top": 305,
          "region": 43,
          "pre": 13,
          "bot": 593,
          "island": 268
        }
      },
      "8": {
        "value": 21.6,
        "rank": {
          "top": 321,
          "region": 43,
          "pre": 13,
          "bot": 579,
          "island": 287
        }
      },
      "9": {
        "value": 5.9,
        "rank": {
          "top": 373,
          "region": 41,
          "pre": 13,
          "bot": 529,
          "island": 334
        }
      },
      "10": {
        "value": 0.0,
        "rank": {
          "top": 904,
          "region": 80,
          "pre": 16,
          "bot": 1,
          "island": 856
        }
      },
      "11": {
        "value": 0.0,
        "rank": {
          "top": 904,
          "region": 80,
          "pre": 16,
          "bot": 1,
          "island": 856
        }
      },
      "12": {
        "value": 0.0,
        "rank": {
          "top": 904,
          "region": 80,
          "pre": 16,
          "bot": 1,
          "island": 856
        }
      },
      "all": {
        "value": 46.7,
        "rank": {
          "top": 338,
          "region": 45,
          "pre": 13,
          "bot": 563,
          "island": 301
        }
      }
    },
    "hitemp_35": {
      "1": {
        "value": 0.0,
        "rank": {
          "top": 904,
          "region": 80,
          "pre": 16,
          "bot": 1,
          "island": 856
        }
      },
      "2": {
        "value": 0.0,
        "rank": {
          "top": 904,
          "region": 80,
          "pre": 16,
          "bot": 1,
          "island": 856
        }
      },
      "3": {
        "value": 0.0,
        "rank": {
          "top": 904,
          "region": 80,
          "pre": 16,
          "bot": 1,
          "island": 856
        }
      },
      "4": {
        "value": 0.0,
        "rank": {
          "top": 904,
          "region": 80,
          "pre": 16,
          "bot": 1,
          "island": 856
        }
      },
      "5": {
        "value": 0.0,
        "rank": {
          "top": 904,
          "region": 80,
          "pre": 16,
          "bot": 1,
          "island": 856
        }
      },
      "6": {
        "value": 0.0,
        "rank": {
          "top": 904,
          "region": 80,
          "pre": 16,
          "bot": 1,
          "island": 856
        }
      },
      "7": {
        "value": 0.9,
        "rank": {
          "top": 281,
          "region": 35,
          "pre": 11,
          "bot": 613,
          "island": 281
        }
      },
      "8": {
        "value": 1.5,
        "rank": {
          "top": 321,
          "region": 44,
          "pre": 12,
          "bot": 573,
          "island": 321
        }
      },
      "9": {
        "value": 0.0,
        "rank": {
          "top": 904,
          "region": 80,
          "pre": 16,
          "bot": 1,
          "island": 856
        }
      },
      "10": {
        "value": 0.0,
        "rank": {
          "top": 904,
          "region": 80,
          "pre": 16,
          "bot": 1,
          "island": 856
        }
      },
      "11": {
        "value": 0.0,
        "rank": {
          "top": 904,
          "region": 80,
          "pre": 16,
          "bot": 1,
          "island": 856
        }
      },
      "12": {
        "value": 0.0,
        "rank": {
          "top": 904,
          "region": 80,
          "pre": 16,
          "bot": 1,
          "island": 856
        }
      },
      "all": {
        "value": 2.4,
        "rank": {
          "top": 321,
          "region": 41,
          "pre": 12,
          "bot": 577,
          "island": 321
        }
      }
    },
    "lwtemp_0": {
      "1": {
        "value": 25.6,
        "rank": {
          "top": 425,
          "region": 17,
          "pre": 6,
          "bot": 476,
          "island": 425
        }
      },
      "2": {
        "value": 22.1,
        "rank": {
          "top": 430,
          "region": 18,
          "pre": 7,
          "bot": 474,
          "island": 430
        }
      },
      "3": {
        "value": 15.7,
        "rank": {
          "top": 397,
          "region": 15,
          "pre": 4,
          "bot": 507,
          "island": 397
        }
      },
      "4": {
        "value": 4.0,
        "rank": {
          "top": 347,
          "region": 15,
          "pre": 4,
          "bot": 552,
          "island": 347
        }
      },
      "5": {
        "value": 0.0,
        "rank": {
          "top": 904,
          "region": 80,
          "pre": 16,
          "bot": 1,
          "island": 856
        }
      },
      "6": {
        "value": 0.0,
        "rank": {
          "top": 904,
          "region": 80,
          "pre": 16,
          "bot": 1,
          "island": 856
        }
      },
      "7": {
        "value": 0.0,
        "rank": {
          "top": 904,
          "region": 80,
          "pre": 16,
          "bot": 1,
          "island": 856
        }
      },
      "8": {
        "value": 0.0,
        "rank": {
          "top": 904,
          "region": 80,
          "pre": 16,
          "bot": 1,
          "island": 856
        }
      },
      "9": {
        "value": 0.0,
        "rank": {
          "top": 904,
          "region": 80,
          "pre": 16,
          "bot": 1,
          "island": 856
        }
      },
      "10": {
        "value": 0.1,
        "rank": {
          "top": 280,
          "region": 11,
          "pre": 3,
          "bot": 572,
          "island": 280
        }
      },
      "11": {
        "value": 6.2,
        "rank": {
          "top": 325,
          "region": 14,
          "pre": 3,
          "bot": 577,
          "island": 325
        }
      },
      "12": {
        "value": 20.9,
        "rank": {
          "top": 372,
          "region": 15,
          "pre": 4,
          "bot": 532,
          "island": 372
        }
      },
      "all": {
        "value": 94.7,
        "rank": {
          "top": 388,
          "region": 15,
          "pre": 4,
          "bot": 517,
          "island": 388
        }
      }
    },
    "lwtemp_25": {
      "1": {
        "value": 0.0,
        "rank": {
          "top": 904,
          "region": 80,
          "pre": 16,
          "bot": 1,
          "island": 856
        }
      },
      "2": {
        "value": 0.0,
        "rank": {
          "top": 904,
          "region": 80,
          "pre": 16,
          "bot": 1,
          "island": 856
        }
      },
      "3": {
        "value": 0.0,
        "rank": {
          "top": 904,
          "region": 80,
          "pre": 16,
          "bot": 1,
          "island": 856
        }
      },
      "4": {
        "value": 0.0,
        "rank": {
          "top": 904,
          "region": 80,
          "pre": 16,
          "bot": 1,
          "island": 856
        }
      },
      "5": {
        "value": 0.0,
        "rank": {
          "top": 904,
          "region": 80,
          "pre": 16,
          "bot": 1,
          "island": 856
        }
      },
      "6": {
        "value": 0.0,
        "rank": {
          "top": 904,
          "region": 80,
          "pre": 16,
          "bot": 1,
          "island": 856
        }
      },
      "7": {
        "value": 0.1,
        "rank": {
          "top": 456,
          "region": 58,
          "pre": 10,
          "bot": 385,
          "island": 408
        }
      },
      "8": {
        "value": 0.5,
        "rank": {
          "top": 443,
          "region": 58,
          "pre": 11,
          "bot": 448,
          "island": 395
        }
      },
      "9": {
        "value": 0.0,
        "rank": {
          "top": 904,
          "region": 80,
          "pre": 16,
          "bot": 1,
          "island": 856
        }
      },
      "10": {
        "value": 0.0,
        "rank": {
          "top": 904,
          "region": 80,
          "pre": 16,
          "bot": 1,
          "island": 856
        }
      },
      "11": {
        "value": 0.0,
        "rank": {
          "top": 904,
          "region": 80,
          "pre": 16,
          "bot": 1,
          "island": 856
        }
      },
      "12": {
        "value": 0.0,
        "rank": {
          "top": 904,
          "region": 80,
          "pre": 16,
          "bot": 1,
          "island": 856
        }
      },
      "all": {
        "value": 0.7,
        "rank": {
          "top": 449,
          "region": 59,
          "pre": 11,
          "bot": 448,
          "island": 401
        }
      }
    },
    "rain_1": {
      "1": {
        "value": 9.6,
        "rank": {
          "top": 605,
          "region": 76,
          "pre": 7,
          "bot": 622
        }
      },
      "2": {
        "value": 10.2,
        "rank": {
          "top": 530,
          "region": 74,
          "pre": 7,
          "bot": 692
        }
      },
      "3": {
        "value": 10.9,
        "rank": {
          "top": 648,
          "region": 78,
          "pre": 7,
          "bot": 561
        }
      },
      "4": {
        "value": 10.2,
        "rank": {
          "top": 631,
          "region": 46,
          "pre": 6,
          "bot": 561
        }
      },
      "5": {
        "value": 10.7,
        "rank": {
          "top": 425,
          "region": 12,
          "pre": 4,
          "bot": 743
        }
      },
      "6": {
        "value": 12.0,
        "rank": {
          "top": 509,
          "region": 37,
          "pre": 6,
          "bot": 698
        }
      },
      "7": {
        "value": 12.8,
        "rank": {
          "top": 481,
          "region": 35,
          "pre": 7,
          "bot": 731
        }
      },
      "8": {
        "value": 9.7,
        "rank": {
          "top": 889,
          "region": 54,
          "pre": 7,
          "bot": 321
        }
      },
      "9": {
        "value": 10.5,
        "rank": {
          "top": 961,
          "region": 51,
          "pre": 6,
          "bot": 243
        }
      },
      "10": {
        "value": 8.0,
        "rank": {
          "top": 1038,
          "region": 63,
          "pre": 6,
          "bot": 178
        }
      },
      "11": {
        "value": 7.7,
        "rank": {
          "top": 857,
          "region": 74,
          "pre": 6,
          "bot": 354
        }
      },
      "12": {
        "value": 9.2,
        "rank": {
          "top": 648,
          "region": 80,
          "pre": 7,
          "bot": 571
        }
      },
      "all": {
        "value": 121.5,
        "rank": {
          "top": 715,
          "region": 74,
          "pre": 7,
          "bot": 515
        }
      }
    },
    "rain_10": {
      "1": {
        "value": 2.0,
        "rank": {
          "top": 679,
          "region": 85,
          "pre": 6,
          "bot": 507
        }
      },
      "2": {
        "value": 2.3,
        "rank": {
          "top": 688,
          "region": 91,
          "pre": 6,
          "bot": 507
        }
      },
      "3": {
        "value": 3.7,
        "rank": {
          "top": 677,
          "region": 89,
          "pre": 6,
          "bot": 533
        }
      },
      "4": {
        "value": 4.3,
        "rank": {
          "top": 465,
          "region": 57,
          "pre": 6,
          "bot": 740
        }
      },
      "5": {
        "value": 4.9,
        "rank": {
          "top": 324,
          "region": 18,
          "pre": 4,
          "bot": 879
        }
      },
      "6": {
        "value": 6.2,
        "rank": {
          "top": 353,
          "region": 32,
          "pre": 3,
          "bot": 860
        }
      },
      "7": {
        "value": 7.3,
        "rank": {
          "top": 194,
          "region": 18,
          "pre": 3,
          "bot": 1021
        }
      },
      "8": {
        "value": 4.5,
        "rank": {
          "top": 702,
          "region": 45,
          "pre": 6,
          "bot": 485
        }
      },
      "9": {
        "value": 5.1,
        "rank": {
          "top": 634,
          "region": 58,
          "pre": 8,
          "bot": 550
        }
      },
      "10": {
        "value": 3.5,
        "rank": {
          "top": 855,
          "region": 43,
          "pre": 7,
          "bot": 324
        }
      },
      "11": {
        "value": 2.4,
        "rank": {
          "top": 952,
          "region": 86,
          "pre": 5,
          "bot": 241
        }
      },
      "12": {
        "value": 2.3,
        "rank": {
          "top": 683,
          "region": 86,
          "pre": 8,
          "bot": 506
        }
      },
      "all": {
        "value": 48.4,
        "rank": {
          "top": 619,
          "region": 73,
          "pre": 6,
          "bot": 610
        }
      }
    },
    "rain_100": {
      "1": {
        "value": 0.0,
        "rank": {
          "top": 1230,
          "region": 121,
          "pre": 25,
          "bot": 1
        }
      },
      "2": {
        "value": 0.0,
        "rank": {
          "top": 1230,
          "region": 121,
          "pre": 25,
          "bot": 1
        }
      },
      "3": {
        "value": 0.0,
        "rank": {
          "top": 1230,
          "region": 121,
          "pre": 25,
          "bot": 1
        }
      },
      "4": {
        "value": 0.0,
        "rank": {
          "top": 1230,
          "region": 121,
          "pre": 25,
          "bot": 1
        }
      },
      "5": {
        "value": 0.0,
        "rank": {
          "top": 1230,
          "region": 121,
          "pre": 25,
          "bot": 1
        }
      },
      "6": {
        "value": 0.1,
        "rank": {
          "top": 419,
          "region": 66,
          "pre": 3,
          "bot": 536
        }
      },
      "7": {
        "value": 0.2,
        "rank": {
          "top": 431,
          "region": 71,
          "pre": 4,
          "bot": 614
        }
      },
      "8": {
        "value": 0.1,
        "rank": {
          "top": 552,
          "region": 36,
          "pre": 2,
          "bot": 270
        }
      },
      "9": {
        "value": 0.1,
        "rank": {
          "top": 676,
          "region": 60,
          "pre": 16,
          "bot": 159
        }
      },
      "10": {
        "value": 0.0,
        "rank": {
          "top": 1230,
          "region": 121,
          "pre": 25,
          "bot": 1
        }
      },
      "11": {
        "value": 0.0,
        "rank": {
          "top": 1230,
          "region": 121,
          "pre": 25,
          "bot": 1
        }
      },
      "12": {
        "value": 0.0,
        "rank": {
          "top": 1230,
          "region": 121,
          "pre": 25,
          "bot": 1
        }
      },
      "all": {
        "value": 0.4,
        "rank": {
          "top": 828,
          "region": 103,
          "pre": 13,
          "bot": 306
        }
      }
    },
    "rain_30": {
      "1": {
        "value": 0.2,
        "rank": {
          "top": 781,
          "region": 68,
          "pre": 4,
          "bot": 275
        }
      },
      "2": {
        "value": 0.1,
        "rank": {
          "top": 804,
          "region": 82,
          "pre": 5,
          "bot": 173
        }
      },
      "3": {
        "value": 0.8,
        "rank": {
          "top": 452,
          "region": 53,
          "pre": 3,
          "bot": 712
        }
      },
      "4": {
        "value": 1.0,
        "rank": {
          "top": 474,
          "region": 57,
          "pre": 7,
          "bot": 705
        }
      },
      "5": {
        "value": 1.7,
        "rank": {
          "top": 316,
          "region": 29,
          "pre": 2,
          "bot": 870
        }
      },
      "6": {
        "value": 1.9,
        "rank": {
          "top": 461,
          "region": 62,
          "pre": 4,
          "bot": 735
        }
      },
      "7": {
        "value": 2.9,
        "rank": {
          "top": 327,
          "region": 54,
          "pre": 3,
          "bot": 878
        }
      },
      "8": {
        "value": 1.4,
        "rank": {
          "top": 843,
          "region": 69,
          "pre": 7,
          "bot": 307
        }
      },
      "9": {
        "value": 2.0,
        "rank": {
          "top": 532,
          "region": 63,
          "pre": 7,
          "bot": 638
        }
      },
      "10": {
        "value": 0.9,
        "rank": {
          "top": 945,
          "region": 82,
          "pre": 9,
          "bot": 202
        }
      },
      "11": {
        "value": 0.3,
        "rank": {
          "top": 967,
          "region": 88,
          "pre": 5,
          "bot": 149
        }
      },
      "12": {
        "value": 0.2,
        "rank": {
          "top": 864,
          "region": 76,
          "pre": 6,
          "bot": 180
        }
      },
      "all": {
        "value": 13.3,
        "rank": {
          "top": 636,
          "region": 74,
          "pre": 6,
          "bot": 585
        }
      }
    },
    "rain_50": {
      "1": {
        "value": 0.0,
        "rank": {
          "top": 1230,
          "region": 121,
          "pre": 25,
          "bot": 1
        }
      },
      "2": {
        "value": 0.0,
        "rank": {
          "top": 1230,
          "region": 121,
          "pre": 25,
          "bot": 1
        }
      },
      "3": {
        "value": 0.0,
        "rank": {
          "top": 1230,
          "region": 121,
          "pre": 25,
          "bot": 1
        }
      },
      "4": {
        "value": 0.2,
        "rank": {
          "top": 518,
          "region": 41,
          "pre": 4,
          "bot": 557
        }
      },
      "5": {
        "value": 0.5,
        "rank": {
          "top": 417,
          "region": 43,
          "pre": 5,
          "bot": 736
        }
      },
      "6": {
        "value": 0.9,
        "rank": {
          "top": 382,
          "region": 40,
          "pre": 2,
          "bot": 800
        }
      },
      "7": {
        "value": 1.2,
        "rank": {
          "top": 396,
          "region": 70,
          "pre": 3,
          "bot": 786
        }
      },
      "8": {
        "value": 0.7,
        "rank": {
          "top": 626,
          "region": 36,
          "pre": 2,
          "bot": 468
        }
      },
      "9": {
        "value": 0.6,
        "rank": {
          "top": 834,
          "region": 106,
          "pre": 19,
          "bot": 312
        }
      },
      "10": {
        "value": 0.2,
        "rank": {
          "top": 1040,
          "region": 114,
          "pre": 20,
          "bot": 92
        }
      },
      "11": {
        "value": 0.1,
        "rank": {
          "top": 623,
          "region": 36,
          "pre": 3,
          "bot": 261
        }
      },
      "12": {
        "value": 0.0,
        "rank": {
          "top": 1230,
          "region": 121,
          "pre": 25,
          "bot": 1
        }
      },
      "all": {
        "value": 4.3,
        "rank": {
          "top": 711,
          "region": 89,
          "pre": 9,
          "bot": 506
        }
      }
    },
    "rain_70": {
      "1": {
        "value": 0.0,
        "rank": {
          "top": 1230,
          "region": 121,
          "pre": 25,
          "bot": 1
        }
      },
      "2": {
        "value": 0.0,
        "rank": {
          "top": 1230,
          "region": 121,
          "pre": 25,
          "bot": 1
        }
      },
      "3": {
        "value": 0.0,
        "rank": {
          "top": 1230,
          "region": 121,
          "pre": 25,
          "bot": 1
        }
      },
      "4": {
        "value": 0.0,
        "rank": {
          "top": 1230,
          "region": 121,
          "pre": 25,
          "bot": 1
        }
      },
      "5": {
        "value": 0.2,
        "rank": {
          "top": 385,
          "region": 28,
          "pre": 2,
          "bot": 664
        }
      },
      "6": {
        "value": 0.3,
        "rank": {
          "top": 466,
          "region": 67,
          "pre": 4,
          "bot": 633
        }
      },
      "7": {
        "value": 0.6,
        "rank": {
          "top": 405,
          "region": 67,
          "pre": 4,
          "bot": 756
        }
      },
      "8": {
        "value": 0.3,
        "rank": {
          "top": 637,
          "region": 35,
          "pre": 1,
          "bot": 356
        }
      },
      "9": {
        "value": 0.2,
        "rank": {
          "top": 913,
          "region": 114,
          "pre": 24,
          "bot": 140
        }
      },
      "10": {
        "value": 0.0,
        "rank": {
          "top": 1230,
          "region": 121,
          "pre": 25,
          "bot": 1
        }
      },
      "11": {
        "value": 0.0,
        "rank": {
          "top": 1230,
          "region": 121,
          "pre": 25,
          "bot": 1
        }
      },
      "12": {
        "value": 0.0,
        "rank": {
          "top": 1230,
          "region": 121,
          "pre": 25,
          "bot": 1
        }
      },
      "all": {
        "value": 1.6,
        "rank": {
          "top": 779,
          "region": 99,
          "pre": 10,
          "bot": 421
        }
      }
    },
    "sm_rain": {
      "1": {
        "value": 60.3,
        "rank": {
          "top": 767,
          "region": 80,
          "pre": 6,
          "bot": 464
        }
      },
      "2": {
        "value": 67.5,
        "rank": {
          "top": 727,
          "region": 86,
          "pre": 6,
          "bot": 504
        }
      },
      "3": {
        "value": 105.1,
        "rank": {
          "top": 680,
          "region": 89,
          "pre": 6,
          "bot": 548
        }
      },
      "4": {
        "value": 120.1,
        "rank": {
          "top": 562,
          "region": 65,
          "pre": 6,
          "bot": 669
        }
      },
      "5": {
        "value": 157.3,
        "rank": {
          "top": 389,
          "region": 31,
          "pre": 4,
          "bot": 841
        }
      },
      "6": {
        "value": 191.3,
        "rank": {
          "top": 475,
          "region": 67,
          "pre": 8,
          "bot": 756
        }
      },
      "7": {
        "value": 253.4,
        "rank": {
          "top": 388,
          "region": 56,
          "pre": 4,
          "bot": 842
        }
      },
      "8": {
        "value": 147.5,
        "rank": {
          "top": 879,
          "region": 61,
          "pre": 6,
          "bot": 352
        }
      },
      "9": {
        "value": 172.6,
        "rank": {
          "top": 784,
          "region": 80,
          "pre": 11,
          "bot": 446
        }
      },
      "10": {
        "value": 103.8,
        "rank": {
          "top": 1079,
          "region": 86,
          "pre": 9,
          "bot": 151
        }
      },
      "11": {
        "value": 67.8,
        "rank": {
          "top": 1028,
          "region": 91,
          "pre": 6,
          "bot": 203
        }
      },
      "12": {
        "value": 64.5,
        "rank": {
          "top": 831,
          "region": 84,
          "pre": 6,
          "bot": 395
        }
      },
      "all": {
        "value": 1511.0,
        "rank": {
          "top": 743,
          "region": 89,
          "pre": 6,
          "bot": 488
        }
      }
    },
    "sm_snowing": {
      "1": {},
      "2": {},
      "3": {},
      "4": {},
      "5": {},
      "6": {},
      "7": {},
      "8": {},
      "9": {},
      "10": {},
      "11": {},
      "12": {},
      "all": {}
    },
    "sm_sun": {
      "1": {
        "value": 109.3,
        "rank": {
          "top": 430,
          "region": 29,
          "pre": 11,
          "bot": 397
        }
      },
      "2": {
        "value": 117.1,
        "rank": {
          "top": 456,
          "region": 33,
          "pre": 12,
          "bot": 372
        }
      },
      "3": {
        "value": 161.4,
        "rank": {
          "top": 396,
          "region": 29,
          "pre": 9,
          "bot": 432
        }
      },
      "4": {
        "value": 185.4,
        "rank": {
          "top": 334,
          "region": 36,
          "pre": 10,
          "bot": 491
        }
      },
      "5": {
        "value": 190.7,
        "rank": {
          "top": 453,
          "region": 72,
          "pre": 14,
          "bot": 369
        }
      },
      "6": {
        "value": 136.9,
        "rank": {
          "top": 569,
          "region": 66,
          "pre": 13,
          "bot": 258
        }
      },
      "7": {
        "value": 137.4,
        "rank": {
          "top": 637,
          "region": 68,
          "pre": 14,
          "bot": 188
        }
      },
      "8": {
        "value": 173.3,
        "rank": {
          "top": 503,
          "region": 67,
          "pre": 13,
          "bot": 324
        }
      },
      "9": {
        "value": 140.9,
        "rank": {
          "top": 534,
          "region": 57,
          "pre": 13,
          "bot": 293
        }
      },
      "10": {
        "value": 150.1,
        "rank": {
          "top": 392,
          "region": 54,
          "pre": 12,
          "bot": 436
        }
      },
      "11": {
        "value": 126.7,
        "rank": {
          "top": 450,
          "region": 35,
          "pre": 11,
          "bot": 378
        }
      },
      "12": {
        "value": 109.1,
        "rank": {
          "top": 441,
          "region": 32,
          "pre": 12,
          "bot": 384
        }
      },
      "all": {
        "value": 1738.3,
        "rank": {
          "top": 472,
          "region": 41,
          "pre": 12,
          "bot": 356
        }
      }
    },
    "snowed_10": {
      "1": {},
      "2": {},
      "3": {},
      "4": {},
      "5": {},
      "6": {},
      "7": {},
      "8": {},
      "9": {},
      "10": {},
      "11": {},
      "12": {},
      "all": {}
    },
    "snowed_100": {
      "1": {},
      "2": {},
      "3": {},
      "4": {},
      "5": {},
      "6": {},
      "7": {},
      "8": {},
      "9": {},
      "10": {},
      "11": {},
      "12": {},
      "all": {}
    },
    "snowed_20": {
      "1": {},
      "2": {},
      "3": {},
      "4": {},
      "5": {},
      "6": {},
      "7": {},
      "8": {},
      "9": {},
      "10": {},
      "11": {},
      "12": {},
      "all": {}
    },
    "snowed_5": {
      "1": {},
      "2": {},
      "3": {},
      "4": {},
      "5": {},
      "6": {},
      "7": {},
      "8": {},
      "9": {},
      "10": {},
      "11": {},
      "12": {},
      "all": {}
    },
    "snowed_50": {
      "1": {},
      "2": {},
      "3": {},
      "4": {},
      "5": {},
      "6": {},
      "7": {},
      "8": {},
      "9": {},
      "10": {},
      "11": {},
      "12": {},
      "all": {}
    },
    "snowing_10": {
      "1": {},
      "2": {},
      "3": {},
      "4": {},
      "5": {},
      "6": {},
      "7": {},
      "8": {},
      "9": {},
      "10": {},
      "11": {},
      "12": {},
      "all": {}
    },
    "snowing_20": {
      "1": {},
      "2": {},
      "3": {},
      "4": {},
      "5": {},
      "6": {},
      "7": {},
      "8": {},
      "9": {},
      "10": {},
      "11": {},
      "12": {},
      "all": {}
    },
    "snowing_3": {
      "1": {},
      "2": {},
      "3": {},
      "4": {},
      "5": {},
      "6": {},
      "7": {},
      "8": {},
      "9": {},
      "10": {},
      "11": {},
      "12": {},
      "all": {}
    },
    "snowing_5": {
      "1": {},
      "2": {},
      "3": {},
      "4": {},
      "5": {},
      "6": {},
      "7": {},
      "8": {},
      "9": {},
      "10": {},
      "11": {},
      "12": {},
      "all": {}
    },
    "snowing_50": {
      "1": {},
      "2": {},
      "3": {},
      "4": {},
      "5": {},
      "6": {},
      "7": {},
      "8": {},
      "9": {},
      "10": {},
      "11": {},
      "12": {},
      "all": {}
    },
    "wind_10": {
      "1": {
        "value": 0.2,
        "rank": {
          "top": 509,
          "region": 38,
          "pre": 4,
          "bot": 320
        }
      },
      "2": {
        "value": 0.2,
        "rank": {
          "top": 546,
          "region": 38,
          "pre": 5,
          "bot": 282
        }
      },
      "3": {
        "value": 0.4,
        "rank": {
          "top": 531,
          "region": 36,
          "pre": 4,
          "bot": 321
        }
      },
      "4": {
        "value": 0.4,
        "rank": {
          "top": 520,
          "region": 39,
          "pre": 5,
          "bot": 323
        }
      },
      "5": {
        "value": 0.2,
        "rank": {
          "top": 478,
          "region": 37,
          "pre": 5,
          "bot": 333
        }
      },
      "6": {
        "value": 0.1,
        "rank": {
          "top": 419,
          "region": 33,
          "pre": 4,
          "bot": 310
        }
      },
      "7": {
        "value": 0.1,
        "rank": {
          "top": 402,
          "region": 38,
          "pre": 4,
          "bot": 347
        }
      },
      "8": {
        "value": 0.2,
        "rank": {
          "top": 422,
          "region": 39,
          "pre": 5,
          "bot": 381
        }
      },
      "9": {
        "value": 0.7,
        "rank": {
          "top": 321,
          "region": 26,
          "pre": 4,
          "bot": 522
        }
      },
      "10": {
        "value": 0.7,
        "rank": {
          "top": 344,
          "region": 23,
          "pre": 3,
          "bot": 510
        }
      },
      "11": {
        "value": 0.2,
        "rank": {
          "top": 469,
          "region": 34,
          "pre": 3,
          "bot": 364
        }
      },
      "12": {
        "value": 0.2,
        "rank": {
          "top": 533,
          "region": 36,
          "pre": 4,
          "bot": 293
        }
      },
      "all": {
        "value": 3.5,
        "rank": {
          "top": 513,
          "region": 38,
          "pre": 5,
          "bot": 357
        }
      }
    },
    "wind_15": {
      "1": {
        "value": 0.0,
        "rank": {
          "top": 874,
          "region": 80,
          "pre": 16,
          "bot": 1
        }
      },
      "2": {
        "value": 0.0,
        "rank": {
          "top": 874,
          "region": 80,
          "pre": 16,
          "bot": 1
        }
      },
      "3": {
        "value": 0.0,
        "rank": {
          "top": 874,
          "region": 80,
          "pre": 16,
          "bot": 1
        }
      },
      "4": {
        "value": 0.1,
        "rank": {
          "top": 197,
          "region": 13,
          "pre": 2,
          "bot": 579
        }
      },
      "5": {
        "value": 0.1,
        "rank": {
          "top": 135,
          "region": 11,
          "pre": 2,
          "bot": 651
        }
      },
      "6": {
        "value": 0.0,
        "rank": {
          "top": 874,
          "region": 80,
          "pre": 16,
          "bot": 1
        }
      },
      "7": {
        "value": 0.0,
        "rank": {
          "top": 874,
          "region": 80,
          "pre": 16,
          "bot": 1
        }
      },
      "8": {
        "value": 0.0,
        "rank": {
          "top": 874,
          "region": 80,
          "pre": 16,
          "bot": 1
        }
      },
      "9": {
        "value": 0.2,
        "rank": {
          "top": 205,
          "region": 19,
          "pre": 2,
          "bot": 588
        }
      },
      "10": {
        "value": 0.3,
        "rank": {
          "top": 140,
          "region": 7,
          "pre": 1,
          "bot": 704
        }
      },
      "11": {
        "value": 0.0,
        "rank": {
          "top": 874,
          "region": 80,
          "pre": 16,
          "bot": 1
        }
      },
      "12": {
        "value": 0.0,
        "rank": {
          "top": 874,
          "region": 80,
          "pre": 16,
          "bot": 1
        }
      },
      "all": {
        "value": 0.8,
        "rank": {
          "top": 265,
          "region": 23,
          "pre": 3,
          "bot": 597
        }
      }
    },
    "wind_20": {
      "1": {
        "value": 0.0,
        "rank": {
          "top": 874,
          "region": 80,
          "pre": 16,
          "bot": 1
        }
      },
      "2": {
        "value": 0.0,
        "rank": {
          "top": 874,
          "region": 80,
          "pre": 16,
          "bot": 1
        }
      },
      "3": {
        "value": 0.0,
        "rank": {
          "top": 874,
          "region": 80,
          "pre": 16,
          "bot": 1
        }
      },
      "4": {
        "value": 0.0,
        "rank": {
          "top": 874,
          "region": 80,
          "pre": 16,
          "bot": 1
        }
      },
      "5": {
        "value": 0.0,
        "rank": {
          "top": 874,
          "region": 80,
          "pre": 16,
          "bot": 1
        }
      },
      "6": {
        "value": 0.0,
        "rank": {
          "top": 874,
          "region": 80,
          "pre": 16,
          "bot": 1
        }
      },
      "7": {
        "value": 0.0,
        "rank": {
          "top": 874,
          "region": 80,
          "pre": 16,
          "bot": 1
        }
      },
      "8": {
        "value": 0.0,
        "rank": {
          "top": 874,
          "region": 80,
          "pre": 16,
          "bot": 1
        }
      },
      "9": {
        "value": 0.1,
        "rank": {
          "top": 116,
          "region": 7,
          "pre": 1,
          "bot": 677
        }
      },
      "10": {
        "value": 0.2,
        "rank": {
          "top": 48,
          "region": 2,
          "pre": 1,
          "bot": 794
        }
      },
      "11": {
        "value": 0.0,
        "rank": {
          "top": 874,
          "region": 80,
          "pre": 16,
          "bot": 1
        }
      },
      "12": {
        "value": 0.0,
        "rank": {
          "top": 874,
          "region": 80,
          "pre": 16,
          "bot": 1
        }
      },
      "all": {
        "value": 0.4,
        "rank": {
          "top": 132,
          "region": 6,
          "pre": 1,
          "bot": 728
        }
      }
    },
    "wind_30": {
      "1": {
        "value": 0.0,
        "rank": {
          "top": 874,
          "region": 80,
          "pre": 16,
          "bot": 1
        }
      },
      "2": {
        "value": 0.0,
        "rank": {
          "top": 874,
          "region": 80,
          "pre": 16,
          "bot": 1
        }
      },
      "3": {
        "value": 0.0,
        "rank": {
          "top": 874,
          "region": 80,
          "pre": 16,
          "bot": 1
        }
      },
      "4": {
        "value": 0.0,
        "rank": {
          "top": 874,
          "region": 80,
          "pre": 16,
          "bot": 1
        }
      },
      "5": {
        "value": 0.0,
        "rank": {
          "top": 874,
          "region": 80,
          "pre": 16,
          "bot": 1
        }
      },
      "6": {
        "value": 0.0,
        "rank": {
          "top": 874,
          "region": 80,
          "pre": 16,
          "bot": 1
        }
      },
      "7": {
        "value": 0.0,
        "rank": {
          "top": 874,
          "region": 80,
          "pre": 16,
          "bot": 1
        }
      },
      "8": {
        "value": 0.0,
        "rank": {
          "top": 874,
          "region": 80,
          "pre": 16,
          "bot": 1
        }
      },
      "9": {
        "value": 0.0,
        "rank": {
          "top": 874,
          "region": 80,
          "pre": 16,
          "bot": 1
        }
      },
      "10": {
        "value": 0.1,
        "rank": {
          "top": 4,
          "region": 1,
          "pre": 1,
          "bot": 850
        }
      },
      "11": {
        "value": 0.0,
        "rank": {
          "top": 874,
          "region": 80,
          "pre": 16,
          "bot": 1
        }
      },
      "12": {
        "value": 0.0,
        "rank": {
          "top": 874,
          "region": 80,
          "pre": 16,
          "bot": 1
        }
      },
      "all": {
        "value": 0.1,
        "rank": {
          "top": 41,
          "region": 1,
          "pre": 1,
          "bot": 805
        }
      }
    }
  },
  "meteo": {
    "11016": {
      "station_name": "稚内",
      "official_name": "稚内地方気象台"
    },
    "12442": {
      "station_name": "旭川",
      "official_name": "旭川地方気象台"
    },
    "14163": {
      "station_name": "札幌",
      "official_name": "札幌管区気象台"
    },
    "17341": {
      "station_name": "網走",
      "official_name": "網走地方気象台"
    },
    "19432": {
      "station_name": "釧路",
      "official_name": "釧路地方気象台"
    },
    "21323": {
      "station_name": "室蘭",
      "official_name": "室蘭地方気象台"
    },
    "23232": {
      "station_name": "函館",
      "official_name": "函館地方気象台"
    },
    "31312": {
      "station_name": "青森",
      "official_name": "青森地方気象台"
    },
    "32402": {
      "station_name": "秋田",
      "official_name": "秋田地方気象台"
    },
    "33431": {
      "station_name": "盛岡",
      "official_name": "盛岡地方気象台"
    },
    "34392": {
      "station_name": "仙台",
      "official_name": "仙台管区気象台"
    },
    "35426": {
      "station_name": "山形",
      "official_name": "山形地方気象台"
    },
    "36127": {
      "station_name": "福島",
      "official_name": "福島地方気象台"
    },
    "40201": {
      "station_name": "水戸",
      "official_name": "水戸地方気象台"
    },
    "40336": {
      "station_name": "つくば",
      "official_name": "高層気象台"
    },
    "41277": {
      "station_name": "宇都宮",
      "official_name": "宇都宮地方気象台"
    },
    "42251": {
      "station_name": "前橋",
      "official_name": "前橋地方気象台"
    },
    "43056": {
      "station_name": "熊谷",
      "official_name": "熊谷地方気象台"
    },
    "44132": {
      "station_name": "東京",
      "official_name": "東京管区気象台"
    },
    "45148": {
      "station_name": "銚子",
      "official_name": "銚子地方気象台"
    },
    "46106": {
      "station_name": "横浜",
      "official_name": "横浜地方気象台"
    },
    "48156": {
      "station_name": "長野",
      "official_name": "長野地方気象台"
    },
    "49142": {
      "station_name": "甲府",
      "official_name": "甲府地方気象台"
    },
    "50331": {
      "station_name": "静岡",
      "official_name": "静岡地方気象台"
    },
    "51106": {
      "station_name": "名古屋",
      "official_name": "名古屋地方気象台"
    },
    "52586": {
      "station_name": "岐阜",
      "official_name": "岐阜地方気象台"
    },
    "53133": {
      "station_name": "津",
      "official_name": "津地方気象台"
    },
    "54232": {
      "station_name": "新潟",
      "official_name": "新潟地方気象台"
    },
    "55102": {
      "station_name": "富山",
      "official_name": "富山地方気象台"
    },
    "56227": {
      "station_name": "金沢",
      "official_name": "金沢地方気象台"
    },
    "57066": {
      "station_name": "福井",
      "official_name": "福井地方気象台"
    },
    "60131": {
      "station_name": "彦根",
      "official_name": "彦根地方気象台"
    },
    "61286": {
      "station_name": "京都",
      "official_name": "京都地方気象台"
    },
    "62078": {
      "station_name": "大阪",
      "official_name": "大阪管区気象台"
    },
    "63518": {
      "station_name": "神戸",
      "official_name": "神戸地方気象台"
    },
    "64036": {
      "station_name": "奈良",
      "official_name": "奈良地方気象台"
    },
    "65042": {
      "station_name": "和歌山",
      "official_name": "和歌山地方気象台"
    },
    "66408": {
      "station_name": "岡山",
      "official_name": "岡山地方気象台"
    },
    "67437": {
      "station_name": "広島",
      "official_name": "広島地方気象台"
    },
    "68132": {
      "station_name": "松江",
      "official_name": "松江地方気象台"
    },
    "69122": {
      "station_name": "鳥取",
      "official_name": "鳥取地方気象台"
    },
    "71106": {
      "station_name": "徳島",
      "official_name": "徳島地方気象台"
    },
    "72086": {
      "station_name": "高松",
      "official_name": "高松地方気象台"
    },
    "73166": {
      "station_name": "松山",
      "official_name": "松山地方気象台"
    },
    "74182": {
      "station_name": "高知",
      "official_name": "高知地方気象台"
    },
    "81428": {
      "station_name": "下関",
      "official_name": "下関地方気象台"
    },
    "82182": {
      "station_name": "福岡",
      "official_name": "福岡管区気象台"
    },
    "83216": {
      "station_name": "大分",
      "official_name": "大分地方気象台"
    },
    "84496": {
      "station_name": "長崎",
      "official_name": "長崎地方気象台"
    },
    "85142": {
      "station_name": "佐賀",
      "official_name": "佐賀地方気象台"
    },
    "86141": {
      "station_name": "熊本",
      "official_name": "熊本地方気象台"
    },
    "87376": {
      "station_name": "宮崎",
      "official_name": "宮崎地方気象台"
    },
    "88317": {
      "station_name": "鹿児島",
      "official_name": "鹿児島地方気象台"
    },
    "91197": {
      "station_name": "那覇",
      "official_name": "沖縄気象台"
    },
    "92011": {
      "station_name": "南大東",
      "official_name": "南大東島地方気象台"
    },
    "93041": {
      "station_name": "宮古島",
      "official_name": "宮古島地方気象台"
    },
    "94081": {
      "station_name": "石垣島",
      "official_name": "石垣島地方気象台"
    }
  },
  "same_pre": {
    "66046": {
      "station_name": "上長田",
      "official_name": "上長田アメダス"
    },
    "66056": {
      "station_name": "恩原",
      "official_name": "恩原アメダス"
    },
    "66091": {
      "station_name": "千屋",
      "official_name": "千屋アメダス"
    },
    "66112": {
      "station_name": "富",
      "official_name": "富アメダス"
    },
    "66127": {
      "station_name": "奈義",
      "official_name": "奈義アメダス"
    },
    "66136": {
      "station_name": "今岡",
      "official_name": "今岡アメダス"
    },
    "66171": {
      "station_name": "久世",
      "official_name": "久世アメダス"
    },
    "66186": {
      "station_name": "津山",
      "official_name": "津山特別地域気象観測所"
    },
    "66221": {
      "station_name": "新見",
      "official_name": "新見アメダス"
    },
    "66226": {
      "station_name": "下呰部",
      "official_name": "下呰部アメダス"
    },
    "66237": {
      "station_name": "旭西",
      "official_name": "旭西アメダス"
    },
    "66251": {
      "station_name": "赤磐",
      "official_name": "赤磐アメダス"
    },
    "66276": {
      "station_name": "陣山",
      "official_name": "陣山アメダス"
    },
    "66287": {
      "station_name": "吉備中央",
      "official_name": "吉備中央アメダス"
    },
    "66296": {
      "station_name": "福渡",
      "official_name": "福渡アメダス"
    },
    "66306": {
      "station_name": "和気",
      "official_name": "和気アメダス"
    },
    "66336": {
      "station_name": "高梁",
      "official_name": "高梁アメダス"
    },
    "66346": {
      "station_name": "日応寺",
      "official_name": "岡山航空気象観測所"
    },
    "66381": {
      "station_name": "佐屋",
      "official_name": "佐屋アメダス"
    },
    "66391": {
      "station_name": "矢掛",
      "official_name": "矢掛アメダス"
    },
    "66408": {
      "station_name": "岡山",
      "official_name": "岡山地方気象台"
    },
    "66421": {
      "station_name": "虫明",
      "official_name": "虫明アメダス"
    },
    "66446": {
      "station_name": "倉敷",
      "official_name": "倉敷アメダス"
    },
    "66481": {
      "station_name": "笠岡",
      "official_name": "笠岡アメダス"
    },
    "66501": {
      "station_name": "玉野",
      "official_name": "玉野アメダス"
    }
  },
  "similar_all": {
    "67376": {
      "similar": 0.973,
      "station_name": "東広島",
      "pref": "広島県",
      "city": "東広島市",
      "official_name": "東広島アメダス"
    },
    "66136": {
      "similar": 0.972,
      "station_name": "今岡",
      "pref": "岡山県",
      "city": "美作市",
      "official_name": "今岡アメダス"
    },
    "66171": {
      "similar": 0.963,
      "station_name": "久世",
      "pref": "岡山県",
      "city": "真庭市",
      "official_name": "久世アメダス"
    },
    "67116": {
      "similar": 0.962,
      "station_name": "庄原",
      "pref": "広島県",
      "city": "庄原市",
      "official_name": "庄原アメダス"
    },
    "67106": {
      "similar": 0.962,
      "station_name": "三次",
      "pref": "広島県",
      "city": "三次市",
      "official_name": "三次アメダス"
    }
  },
  "similar_meteo": {
    "36127": {
      "similar": 0.911,
      "station_name": "福島",
      "pref": "福島県",
      "city": "福島市",
      "official_name": "福島地方気象台"
    },
    "41277": {
      "similar": 0.904,
      "station_name": "宇都宮",
      "pref": "栃木県",
      "city": "宇都宮市",
      "official_name": "宇都宮地方気象台"
    },
    "60131": {
      "similar": 0.898,
      "station_name": "彦根",
      "pref": "滋賀県",
      "city": "彦根市",
      "official_name": "彦根地方気象台"
    },
    "40201": {
      "similar": 0.894,
      "station_name": "水戸",
      "pref": "茨城県",
      "city": "水戸市",
      "official_name": "水戸地方気象台"
    },
    "61286": {
      "similar": 0.89,
      "station_name": "京都",
      "pref": "京都府",
      "city": "京都市",
      "official_name": "京都地方気象台"
    }
  }
}