{
  "number": "87206",
  "station_name": "神門",
  "kana_name": "ﾐｶﾄﾞ",
  "lon": 32.385,
  "lat": 131.332,
  "height": 250,
  "official_name": "神門アメダス",
  "pref": "宮崎県",
  "city": "東臼杵郡美郷町",
  "data": {
    "av_avtemp": {
      "1": {
        "value": 3.9,
        "rank": {
          "top": 317,
          "region": 105,
          "pre": 13,
          "bot": 583,
          "island": 269
        }
      },
      "2": {
        "value": 5.6,
        "rank": {
          "top": 236,
          "region": 99,
          "pre": 13,
          "bot": 661,
          "island": 188
        }
      },
      "3": {
        "value": 9.2,
        "rank": {
          "top": 207,
          "region": 96,
          "pre": 13,
          "bot": 690,
          "island": 159
        }
      },
      "4": {
        "value": 13.9,
        "rank": {
          "top": 213,
          "region": 91,
          "pre": 13,
          "bot": 676,
          "island": 165
        }
      },
      "5": {
        "value": 18.1,
        "rank": {
          "top": 281,
          "region": 101,
          "pre": 13,
          "bot": 610,
          "island": 233
        }
      },
      "6": {
        "value": 21.3,
        "rank": {
          "top": 327,
          "region": 100,
          "pre": 13,
          "bot": 565,
          "island": 282
        }
      },
      "7": {
        "value": 25.2,
        "rank": {
          "top": 321,
          "region": 100,
          "pre": 12,
          "bot": 569,
          "island": 277
        }
      },
      "8": {
        "value": 25.5,
        "rank": {
          "top": 432,
          "region": 107,
          "pre": 13,
          "bot": 461,
          "island": 384
        }
      },
      "9": {
        "value": 22.4,
        "rank": {
          "top": 361,
          "region": 106,
          "pre": 13,
          "bot": 534,
          "island": 313
        }
      },
      "10": {
        "value": 17.0,
        "rank": {
          "top": 331,
          "region": 104,
          "pre": 13,
          "bot": 564,
          "island": 283
        }
      },
      "11": {
        "value": 11.2,
        "rank": {
          "top": 333,
          "region": 104,
          "pre": 13,
          "bot": 564,
          "island": 285
        }
      },
      "12": {
        "value": 5.7,
        "rank": {
          "top": 354,
          "region": 106,
          "pre": 13,
          "bot": 543,
          "island": 306
        }
      },
      "all": {
        "value": 14.9,
        "rank": {
          "top": 311,
          "region": 104,
          "pre": 13,
          "bot": 586,
          "island": 263
        }
      }
    },
    "av_hitemp": {
      "1": {
        "value": 11.8,
        "rank": {
          "top": 73,
          "region": 35,
          "pre": 10,
          "bot": 829,
          "island": 29
        }
      },
      "2": {
        "value": 13.3,
        "rank": {
          "top": 61,
          "region": 32,
          "pre": 9,
          "bot": 840,
          "island": 19
        }
      },
      "3": {
        "value": 16.5,
        "rank": {
          "top": 58,
          "region": 32,
          "pre": 9,
          "bot": 845,
          "island": 19
        }
      },
      "4": {
        "value": 21.4,
        "rank": {
          "top": 46,
          "region": 20,
          "pre": 2,
          "bot": 855,
          "island": 11
        }
      },
      "5": {
        "value": 25.1,
        "rank": {
          "top": 66,
          "region": 35,
          "pre": 4,
          "bot": 832,
          "island": 34
        }
      },
      "6": {
        "value": 26.7,
        "rank": {
          "top": 168,
          "region": 61,
          "pre": 4,
          "bot": 720,
          "island": 131
        }
      },
      "7": {
        "value": 31.2,
        "rank": {
          "top": 84,
          "region": 33,
          "pre": 4,
          "bot": 809,
          "island": 56
        }
      },
      "8": {
        "value": 31.6,
        "rank": {
          "top": 221,
          "region": 66,
          "pre": 6,
          "bot": 664,
          "island": 201
        }
      },
      "9": {
        "value": 28.4,
        "rank": {
          "top": 168,
          "region": 72,
          "pre": 13,
          "bot": 728,
          "island": 131
        }
      },
      "10": {
        "value": 24.1,
        "rank": {
          "top": 96,
          "region": 57,
          "pre": 12,
          "bot": 804,
          "island": 56
        }
      },
      "11": {
        "value": 18.9,
        "rank": {
          "top": 84,
          "region": 40,
          "pre": 10,
          "bot": 819,
          "island": 40
        }
      },
      "12": {
        "value": 13.7,
        "rank": {
          "top": 93,
          "region": 40,
          "pre": 10,
          "bot": 809,
          "island": 48
        }
      },
      "all": {
        "value": 21.9,
        "rank": {
          "top": 65,
          "region": 37,
          "pre": 9,
          "bot": 837,
          "island": 26
        }
      }
    },
    "av_lwtemp": {
      "1": {
        "value": -2.0,
        "rank": {
          "top": 450,
          "region": 110,
          "pre": 14,
          "bot": 450,
          "island": 402
        }
      },
      "2": {
        "value": -0.6,
        "rank": {
          "top": 371,
          "region": 108,
          "pre": 14,
          "bot": 526,
          "island": 323
        }
      },
      "3": {
        "value": 2.8,
        "rank": {
          "top": 314,
          "region": 104,
          "pre": 13,
          "bot": 583,
          "island": 266
        }
      },
      "4": {
        "value": 7.2,
        "rank": {
          "top": 341,
          "region": 105,
          "pre": 13,
          "bot": 554,
          "island": 293
        }
      },
      "5": {
        "value": 12.1,
        "rank": {
          "top": 379,
          "region": 106,
          "pre": 13,
          "bot": 518,
          "island": 331
        }
      },
      "6": {
        "value": 17.3,
        "rank": {
          "top": 355,
          "region": 107,
          "pre": 13,
          "bot": 539,
          "island": 307
        }
      },
      "7": {
        "value": 21.0,
        "rank": {
          "top": 419,
          "region": 110,
          "pre": 14,
          "bot": 477,
          "island": 371
        }
      },
      "8": {
        "value": 21.4,
        "rank": {
          "top": 455,
          "region": 108,
          "pre": 13,
          "bot": 444,
          "island": 407
        }
      },
      "9": {
        "value": 18.3,
        "rank": {
          "top": 385,
          "region": 105,
          "pre": 13,
          "bot": 513,
          "island": 337
        }
      },
      "10": {
        "value": 11.9,
        "rank": {
          "top": 396,
          "region": 104,
          "pre": 13,
          "bot": 501,
          "island": 348
        }
      },
      "11": {
        "value": 5.7,
        "rank": {
          "top": 400,
          "region": 105,
          "pre": 13,
          "bot": 495,
          "island": 352
        }
      },
      "12": {
        "value": 0.0,
        "rank": {
          "top": 460,
          "region": 109,
          "pre": 14,
          "bot": 439,
          "island": 412
        }
      },
      "all": {
        "value": 9.6,
        "rank": {
          "top": 393,
          "region": 106,
          "pre": 13,
          "bot": 500,
          "island": 345
        }
      }
    },
    "av_wind": {
      "1": {
        "value": 0.6,
        "rank": {
          "top": 866,
          "region": 116,
          "pre": 15,
          "bot": 4
        }
      },
      "2": {
        "value": 0.6,
        "rank": {
          "top": 871,
          "region": 116,
          "pre": 15,
          "bot": 4
        }
      },
      "3": {
        "value": 0.7,
        "rank": {
          "top": 870,
          "region": 116,
          "pre": 15,
          "bot": 3
        }
      },
      "4": {
        "value": 0.7,
        "rank": {
          "top": 870,
          "region": 116,
          "pre": 15,
          "bot": 3
        }
      },
      "5": {
        "value": 0.6,
        "rank": {
          "top": 870,
          "region": 116,
          "pre": 15,
          "bot": 4
        }
      },
      "6": {
        "value": 0.5,
        "rank": {
          "top": 868,
          "region": 116,
          "pre": 15,
          "bot": 5
        }
      },
      "7": {
        "value": 0.6,
        "rank": {
          "top": 860,
          "region": 116,
          "pre": 15,
          "bot": 8
        }
      },
      "8": {
        "value": 0.7,
        "rank": {
          "top": 849,
          "region": 115,
          "pre": 15,
          "bot": 12
        }
      },
      "9": {
        "value": 0.6,
        "rank": {
          "top": 856,
          "region": 115,
          "pre": 15,
          "bot": 10
        }
      },
      "10": {
        "value": 0.5,
        "rank": {
          "top": 866,
          "region": 116,
          "pre": 15,
          "bot": 4
        }
      },
      "11": {
        "value": 0.5,
        "rank": {
          "top": 871,
          "region": 116,
          "pre": 15,
          "bot": 4
        }
      },
      "12": {
        "value": 0.5,
        "rank": {
          "top": 871,
          "region": 116,
          "pre": 15,
          "bot": 3
        }
      },
      "all": {
        "value": 0.6,
        "rank": {
          "top": 869,
          "region": 116,
          "pre": 15,
          "bot": 4
        }
      }
    },
    "hitemp_0": {
      "1": {
        "value": 0.0,
        "rank": {
          "top": 904,
          "region": 116,
          "pre": 15,
          "bot": 1,
          "island": 856
        }
      },
      "2": {
        "value": 0.0,
        "rank": {
          "top": 904,
          "region": 116,
          "pre": 15,
          "bot": 1,
          "island": 856
        }
      },
      "3": {
        "value": 0.0,
        "rank": {
          "top": 904,
          "region": 116,
          "pre": 15,
          "bot": 1,
          "island": 856
        }
      },
      "4": {
        "value": 0.0,
        "rank": {
          "top": 904,
          "region": 116,
          "pre": 15,
          "bot": 1,
          "island": 856
        }
      },
      "5": {
        "value": 0.0,
        "rank": {
          "top": 904,
          "region": 116,
          "pre": 15,
          "bot": 1,
          "island": 856
        }
      },
      "6": {
        "value": 0.0,
        "rank": {
          "top": 904,
          "region": 116,
          "pre": 15,
          "bot": 1,
          "island": 856
        }
      },
      "7": {
        "value": 0.0,
        "rank": {
          "top": 904,
          "region": 116,
          "pre": 15,
          "bot": 1,
          "island": 856
        }
      },
      "8": {
        "value": 0.0,
        "rank": {
          "top": 904,
          "region": 116,
          "pre": 15,
          "bot": 1,
          "island": 856
        }
      },
      "9": {
        "value": 0.0,
        "rank": {
          "top": 904,
          "region": 116,
          "pre": 15,
          "bot": 1,
          "island": 856
        }
      },
      "10": {
        "value": 0.0,
        "rank": {
          "top": 904,
          "region": 116,
          "pre": 15,
          "bot": 1,
          "island": 856
        }
      },
      "11": {
        "value": 0.0,
        "rank": {
          "top": 904,
          "region": 116,
          "pre": 15,
          "bot": 1,
          "island": 856
        }
      },
      "12": {
        "value": 0.0,
        "rank": {
          "top": 904,
          "region": 116,
          "pre": 15,
          "bot": 1,
          "island": 856
        }
      },
      "all": {
        "value": 0.0,
        "rank": {
          "top": 904,
          "region": 116,
          "pre": 15,
          "bot": 1,
          "island": 856
        }
      }
    },
    "hitemp_25": {
      "1": {
        "value": 0.0,
        "rank": {
          "top": 904,
          "region": 116,
          "pre": 15,
          "bot": 1,
          "island": 856
        }
      },
      "2": {
        "value": 0.0,
        "rank": {
          "top": 904,
          "region": 116,
          "pre": 15,
          "bot": 1,
          "island": 856
        }
      },
      "3": {
        "value": 0.5,
        "rank": {
          "top": 35,
          "region": 10,
          "pre": 2,
          "bot": 868,
          "island": 2
        }
      },
      "4": {
        "value": 5.8,
        "rank": {
          "top": 28,
          "region": 5,
          "pre": 1,
          "bot": 876,
          "island": 2
        }
      },
      "5": {
        "value": 17.5,
        "rank": {
          "top": 58,
          "region": 30,
          "pre": 3,
          "bot": 846,
          "island": 26
        }
      },
      "6": {
        "value": 20.0,
        "rank": {
          "top": 266,
          "region": 86,
          "pre": 12,
          "bot": 637,
          "island": 227
        }
      },
      "7": {
        "value": 29.6,
        "rank": {
          "top": 154,
          "region": 75,
          "pre": 11,
          "bot": 735,
          "island": 113
        }
      },
      "8": {
        "value": 30.3,
        "rank": {
          "top": 284,
          "region": 99,
          "pre": 13,
          "bot": 605,
          "island": 242
        }
      },
      "9": {
        "value": 25.6,
        "rank": {
          "top": 210,
          "region": 84,
          "pre": 13,
          "bot": 685,
          "island": 167
        }
      },
      "10": {
        "value": 13.1,
        "rank": {
          "top": 86,
          "region": 51,
          "pre": 12,
          "bot": 818,
          "island": 46
        }
      },
      "11": {
        "value": 0.8,
        "rank": {
          "top": 80,
          "region": 50,
          "pre": 10,
          "bot": 823,
          "island": 41
        }
      },
      "12": {
        "value": 0.0,
        "rank": {
          "top": 904,
          "region": 116,
          "pre": 15,
          "bot": 1,
          "island": 856
        }
      },
      "all": {
        "value": 143.2,
        "rank": {
          "top": 84,
          "region": 49,
          "pre": 8,
          "bot": 821,
          "island": 47
        }
      }
    },
    "hitemp_30": {
      "1": {
        "value": 0.0,
        "rank": {
          "top": 904,
          "region": 116,
          "pre": 15,
          "bot": 1,
          "island": 856
        }
      },
      "2": {
        "value": 0.0,
        "rank": {
          "top": 904,
          "region": 116,
          "pre": 15,
          "bot": 1,
          "island": 856
        }
      },
      "3": {
        "value": 0.0,
        "rank": {
          "top": 904,
          "region": 116,
          "pre": 15,
          "bot": 1,
          "island": 856
        }
      },
      "4": {
        "value": 0.2,
        "rank": {
          "top": 18,
          "region": 4,
          "pre": 2,
          "bot": 849,
          "island": 9
        }
      },
      "5": {
        "value": 2.3,
        "rank": {
          "top": 39,
          "region": 11,
          "pre": 2,
          "bot": 861,
          "island": 24
        }
      },
      "6": {
        "value": 5.6,
        "rank": {
          "top": 118,
          "region": 34,
          "pre": 3,
          "bot": 782,
          "island": 85
        }
      },
      "7": {
        "value": 21.0,
        "rank": {
          "top": 81,
          "region": 37,
          "pre": 4,
          "bot": 821,
          "island": 48
        }
      },
      "8": {
        "value": 22.7,
        "rank": {
          "top": 269,
          "region": 84,
          "pre": 12,
          "bot": 631,
          "island": 236
        }
      },
      "9": {
        "value": 10.4,
        "rank": {
          "top": 153,
          "region": 63,
          "pre": 10,
          "bot": 752,
          "island": 119
        }
      },
      "10": {
        "value": 0.7,
        "rank": {
          "top": 81,
          "region": 48,
          "pre": 5,
          "bot": 807,
          "island": 48
        }
      },
      "11": {
        "value": 0.0,
        "rank": {
          "top": 904,
          "region": 116,
          "pre": 15,
          "bot": 1,
          "island": 856
        }
      },
      "12": {
        "value": 0.0,
        "rank": {
          "top": 904,
          "region": 116,
          "pre": 15,
          "bot": 1,
          "island": 856
        }
      },
      "all": {
        "value": 62.9,
        "rank": {
          "top": 126,
          "region": 52,
          "pre": 6,
          "bot": 779,
          "island": 94
        }
      }
    },
    "hitemp_35": {
      "1": {
        "value": 0.0,
        "rank": {
          "top": 904,
          "region": 116,
          "pre": 15,
          "bot": 1,
          "island": 856
        }
      },
      "2": {
        "value": 0.0,
        "rank": {
          "top": 904,
          "region": 116,
          "pre": 15,
          "bot": 1,
          "island": 856
        }
      },
      "3": {
        "value": 0.0,
        "rank": {
          "top": 904,
          "region": 116,
          "pre": 15,
          "bot": 1,
          "island": 856
        }
      },
      "4": {
        "value": 0.0,
        "rank": {
          "top": 904,
          "region": 116,
          "pre": 15,
          "bot": 1,
          "island": 856
        }
      },
      "5": {
        "value": 0.0,
        "rank": {
          "top": 904,
          "region": 116,
          "pre": 15,
          "bot": 1,
          "island": 856
        }
      },
      "6": {
        "value": 0.0,
        "rank": {
          "top": 904,
          "region": 116,
          "pre": 15,
          "bot": 1,
          "island": 856
        }
      },
      "7": {
        "value": 3.6,
        "rank": {
          "top": 67,
          "region": 9,
          "pre": 2,
          "bot": 833,
          "island": 67
        }
      },
      "8": {
        "value": 3.3,
        "rank": {
          "top": 180,
          "region": 35,
          "pre": 4,
          "bot": 720,
          "island": 180
        }
      },
      "9": {
        "value": 0.1,
        "rank": {
          "top": 269,
          "region": 38,
          "pre": 5,
          "bot": 499,
          "island": 269
        }
      },
      "10": {
        "value": 0.0,
        "rank": {
          "top": 904,
          "region": 116,
          "pre": 15,
          "bot": 1,
          "island": 856
        }
      },
      "11": {
        "value": 0.0,
        "rank": {
          "top": 904,
          "region": 116,
          "pre": 15,
          "bot": 1,
          "island": 856
        }
      },
      "12": {
        "value": 0.0,
        "rank": {
          "top": 904,
          "region": 116,
          "pre": 15,
          "bot": 1,
          "island": 856
        }
      },
      "all": {
        "value": 7.1,
        "rank": {
          "top": 131,
          "region": 19,
          "pre": 2,
          "bot": 771,
          "island": 131
        }
      }
    },
    "lwtemp_0": {
      "1": {
        "value": 22.8,
        "rank": {
          "top": 496,
          "region": 9,
          "pre": 2,
          "bot": 407,
          "island": 496
        }
      },
      "2": {
        "value": 17.7,
        "rank": {
          "top": 535,
          "region": 9,
          "pre": 2,
          "bot": 368,
          "island": 535
        }
      },
      "3": {
        "value": 10.1,
        "rank": {
          "top": 505,
          "region": 9,
          "pre": 2,
          "bot": 397,
          "island": 505
        }
      },
      "4": {
        "value": 1.5,
        "rank": {
          "top": 471,
          "region": 9,
          "pre": 3,
          "bot": 428,
          "island": 471
        }
      },
      "5": {
        "value": 0.0,
        "rank": {
          "top": 904,
          "region": 116,
          "pre": 15,
          "bot": 1,
          "island": 856
        }
      },
      "6": {
        "value": 0.0,
        "rank": {
          "top": 904,
          "region": 116,
          "pre": 15,
          "bot": 1,
          "island": 856
        }
      },
      "7": {
        "value": 0.0,
        "rank": {
          "top": 904,
          "region": 116,
          "pre": 15,
          "bot": 1,
          "island": 856
        }
      },
      "8": {
        "value": 0.0,
        "rank": {
          "top": 904,
          "region": 116,
          "pre": 15,
          "bot": 1,
          "island": 856
        }
      },
      "9": {
        "value": 0.0,
        "rank": {
          "top": 904,
          "region": 116,
          "pre": 15,
          "bot": 1,
          "island": 856
        }
      },
      "10": {
        "value": 0.0,
        "rank": {
          "top": 904,
          "region": 116,
          "pre": 15,
          "bot": 1,
          "island": 856
        }
      },
      "11": {
        "value": 2.9,
        "rank": {
          "top": 423,
          "region": 12,
          "pre": 3,
          "bot": 480,
          "island": 423
        }
      },
      "12": {
        "value": 17.9,
        "rank": {
          "top": 424,
          "region": 7,
          "pre": 2,
          "bot": 480,
          "island": 424
        }
      },
      "all": {
        "value": 72.9,
        "rank": {
          "top": 476,
          "region": 9,
          "pre": 2,
          "bot": 427,
          "island": 476
        }
      }
    },
    "lwtemp_25": {
      "1": {
        "value": 0.0,
        "rank": {
          "top": 904,
          "region": 116,
          "pre": 15,
          "bot": 1,
          "island": 856
        }
      },
      "2": {
        "value": 0.0,
        "rank": {
          "top": 904,
          "region": 116,
          "pre": 15,
          "bot": 1,
          "island": 856
        }
      },
      "3": {
        "value": 0.0,
        "rank": {
          "top": 904,
          "region": 116,
          "pre": 15,
          "bot": 1,
          "island": 856
        }
      },
      "4": {
        "value": 0.0,
        "rank": {
          "top": 904,
          "region": 116,
          "pre": 15,
          "bot": 1,
          "island": 856
        }
      },
      "5": {
        "value": 0.0,
        "rank": {
          "top": 904,
          "region": 116,
          "pre": 15,
          "bot": 1,
          "island": 856
        }
      },
      "6": {
        "value": 0.0,
        "rank": {
          "top": 904,
          "region": 116,
          "pre": 15,
          "bot": 1,
          "island": 856
        }
      },
      "7": {
        "value": 0.0,
        "rank": {
          "top": 904,
          "region": 116,
          "pre": 15,
          "bot": 1,
          "island": 856
        }
      },
      "8": {
        "value": 0.0,
        "rank": {
          "top": 904,
          "region": 116,
          "pre": 15,
          "bot": 1,
          "island": 856
        }
      },
      "9": {
        "value": 0.0,
        "rank": {
          "top": 904,
          "region": 116,
          "pre": 15,
          "bot": 1,
          "island": 856
        }
      },
      "10": {
        "value": 0.0,
        "rank": {
          "top": 904,
          "region": 116,
          "pre": 15,
          "bot": 1,
          "island": 856
        }
      },
      "11": {
        "value": 0.0,
        "rank": {
          "top": 904,
          "region": 116,
          "pre": 15,
          "bot": 1,
          "island": 856
        }
      },
      "12": {
        "value": 0.0,
        "rank": {
          "top": 904,
          "region": 116,
          "pre": 15,
          "bot": 1,
          "island": 856
        }
      },
      "all": {
        "value": 0.1,
        "rank": {
          "top": 537,
          "region": 109,
          "pre": 13,
          "bot": 302,
          "island": 489
        }
      }
    },
    "rain_1": {
      "1": {
        "value": 6.2,
        "rank": {
          "top": 915,
          "region": 121,
          "pre": 13,
          "bot": 308
        }
      },
      "2": {
        "value": 7.8,
        "rank": {
          "top": 791,
          "region": 127,
          "pre": 15,
          "bot": 429
        }
      },
      "3": {
        "value": 11.0,
        "rank": {
          "top": 633,
          "region": 69,
          "pre": 10,
          "bot": 584
        }
      },
      "4": {
        "value": 10.6,
        "rank": {
          "top": 507,
          "region": 50,
          "pre": 9,
          "bot": 695
        }
      },
      "5": {
        "value": 11.0,
        "rank": {
          "top": 321,
          "region": 26,
          "pre": 4,
          "bot": 888
        }
      },
      "6": {
        "value": 16.9,
        "rank": {
          "top": 22,
          "region": 22,
          "pre": 7,
          "bot": 1204
        }
      },
      "7": {
        "value": 14.2,
        "rank": {
          "top": 215,
          "region": 19,
          "pre": 9,
          "bot": 1002
        }
      },
      "8": {
        "value": 13.7,
        "rank": {
          "top": 55,
          "region": 11,
          "pre": 7,
          "bot": 1164
        }
      },
      "9": {
        "value": 13.5,
        "rank": {
          "top": 135,
          "region": 11,
          "pre": 6,
          "bot": 1071
        }
      },
      "10": {
        "value": 8.6,
        "rank": {
          "top": 959,
          "region": 28,
          "pre": 7,
          "bot": 262
        }
      },
      "11": {
        "value": 7.4,
        "rank": {
          "top": 919,
          "region": 119,
          "pre": 16,
          "bot": 290
        }
      },
      "12": {
        "value": 6.2,
        "rank": {
          "top": 985,
          "region": 125,
          "pre": 11,
          "bot": 233
        }
      },
      "all": {
        "value": 127.1,
        "rank": {
          "top": 607,
          "region": 46,
          "pre": 8,
          "bot": 621
        }
      }
    },
    "rain_10": {
      "1": {
        "value": 2.6,
        "rank": {
          "top": 472,
          "region": 63,
          "pre": 8,
          "bot": 732
        }
      },
      "2": {
        "value": 3.8,
        "rank": {
          "top": 262,
          "region": 45,
          "pre": 12,
          "bot": 945
        }
      },
      "3": {
        "value": 6.0,
        "rank": {
          "top": 107,
          "region": 21,
          "pre": 5,
          "bot": 1114
        }
      },
      "4": {
        "value": 5.6,
        "rank": {
          "top": 104,
          "region": 34,
          "pre": 5,
          "bot": 1101
        }
      },
      "5": {
        "value": 6.1,
        "rank": {
          "top": 83,
          "region": 18,
          "pre": 6,
          "bot": 1138
        }
      },
      "6": {
        "value": 10.6,
        "rank": {
          "top": 42,
          "region": 41,
          "pre": 14,
          "bot": 1189
        }
      },
      "7": {
        "value": 8.8,
        "rank": {
          "top": 39,
          "region": 17,
          "pre": 6,
          "bot": 1188
        }
      },
      "8": {
        "value": 8.0,
        "rank": {
          "top": 9,
          "region": 2,
          "pre": 2,
          "bot": 1220
        }
      },
      "9": {
        "value": 7.4,
        "rank": {
          "top": 58,
          "region": 7,
          "pre": 3,
          "bot": 1163
        }
      },
      "10": {
        "value": 4.2,
        "rank": {
          "top": 602,
          "region": 20,
          "pre": 8,
          "bot": 597
        }
      },
      "11": {
        "value": 3.1,
        "rank": {
          "top": 640,
          "region": 73,
          "pre": 11,
          "bot": 555
        }
      },
      "12": {
        "value": 2.2,
        "rank": {
          "top": 726,
          "region": 101,
          "pre": 13,
          "bot": 460
        }
      },
      "all": {
        "value": 68.2,
        "rank": {
          "top": 163,
          "region": 20,
          "pre": 6,
          "bot": 1068
        }
      }
    },
    "rain_100": {
      "1": {
        "value": 0.0,
        "rank": {
          "top": 1230,
          "region": 147,
          "pre": 23,
          "bot": 1
        }
      },
      "2": {
        "value": 0.0,
        "rank": {
          "top": 1230,
          "region": 147,
          "pre": 23,
          "bot": 1
        }
      },
      "3": {
        "value": 0.0,
        "rank": {
          "top": 1230,
          "region": 147,
          "pre": 23,
          "bot": 1
        }
      },
      "4": {
        "value": 0.0,
        "rank": {
          "top": 1230,
          "region": 147,
          "pre": 23,
          "bot": 1
        }
      },
      "5": {
        "value": 0.3,
        "rank": {
          "top": 77,
          "region": 29,
          "pre": 8,
          "bot": 1092
        }
      },
      "6": {
        "value": 1.0,
        "rank": {
          "top": 61,
          "region": 54,
          "pre": 12,
          "bot": 1165
        }
      },
      "7": {
        "value": 1.2,
        "rank": {
          "top": 25,
          "region": 21,
          "pre": 6,
          "bot": 1195
        }
      },
      "8": {
        "value": 1.7,
        "rank": {
          "top": 3,
          "region": 1,
          "pre": 1,
          "bot": 1227
        }
      },
      "9": {
        "value": 1.4,
        "rank": {
          "top": 11,
          "region": 1,
          "pre": 1,
          "bot": 1217
        }
      },
      "10": {
        "value": 0.4,
        "rank": {
          "top": 98,
          "region": 8,
          "pre": 6,
          "bot": 1058
        }
      },
      "11": {
        "value": 0.0,
        "rank": {
          "top": 1230,
          "region": 147,
          "pre": 23,
          "bot": 1
        }
      },
      "12": {
        "value": 0.1,
        "rank": {
          "top": 16,
          "region": 4,
          "pre": 1,
          "bot": 1072
        }
      },
      "all": {
        "value": 6.1,
        "rank": {
          "top": 20,
          "region": 5,
          "pre": 4,
          "bot": 1210
        }
      }
    },
    "rain_30": {
      "1": {
        "value": 0.5,
        "rank": {
          "top": 334,
          "region": 38,
          "pre": 8,
          "bot": 781
        }
      },
      "2": {
        "value": 1.0,
        "rank": {
          "top": 114,
          "region": 32,
          "pre": 7,
          "bot": 1079
        }
      },
      "3": {
        "value": 1.7,
        "rank": {
          "top": 117,
          "region": 21,
          "pre": 5,
          "bot": 1087
        }
      },
      "4": {
        "value": 2.2,
        "rank": {
          "top": 104,
          "region": 34,
          "pre": 9,
          "bot": 1108
        }
      },
      "5": {
        "value": 2.6,
        "rank": {
          "top": 99,
          "region": 31,
          "pre": 11,
          "bot": 1110
        }
      },
      "6": {
        "value": 6.0,
        "rank": {
          "top": 46,
          "region": 45,
          "pre": 14,
          "bot": 1183
        }
      },
      "7": {
        "value": 4.5,
        "rank": {
          "top": 53,
          "region": 32,
          "pre": 8,
          "bot": 1169
        }
      },
      "8": {
        "value": 4.4,
        "rank": {
          "top": 4,
          "region": 2,
          "pre": 2,
          "bot": 1227
        }
      },
      "9": {
        "value": 3.8,
        "rank": {
          "top": 53,
          "region": 5,
          "pre": 4,
          "bot": 1170
        }
      },
      "10": {
        "value": 2.0,
        "rank": {
          "top": 206,
          "region": 16,
          "pre": 8,
          "bot": 989
        }
      },
      "11": {
        "value": 0.9,
        "rank": {
          "top": 357,
          "region": 49,
          "pre": 8,
          "bot": 819
        }
      },
      "12": {
        "value": 0.6,
        "rank": {
          "top": 359,
          "region": 48,
          "pre": 10,
          "bot": 783
        }
      },
      "all": {
        "value": 30.2,
        "rank": {
          "top": 54,
          "region": 15,
          "pre": 5,
          "bot": 1177
        }
      }
    },
    "rain_50": {
      "1": {
        "value": 0.1,
        "rank": {
          "top": 277,
          "region": 40,
          "pre": 12,
          "bot": 634
        }
      },
      "2": {
        "value": 0.1,
        "rank": {
          "top": 257,
          "region": 61,
          "pre": 15,
          "bot": 718
        }
      },
      "3": {
        "value": 0.5,
        "rank": {
          "top": 138,
          "region": 22,
          "pre": 4,
          "bot": 1052
        }
      },
      "4": {
        "value": 0.9,
        "rank": {
          "top": 107,
          "region": 35,
          "pre": 9,
          "bot": 1089
        }
      },
      "5": {
        "value": 1.3,
        "rank": {
          "top": 90,
          "region": 30,
          "pre": 9,
          "bot": 1112
        }
      },
      "6": {
        "value": 3.8,
        "rank": {
          "top": 42,
          "region": 41,
          "pre": 12,
          "bot": 1184
        }
      },
      "7": {
        "value": 2.8,
        "rank": {
          "top": 48,
          "region": 31,
          "pre": 7,
          "bot": 1178
        }
      },
      "8": {
        "value": 2.9,
        "rank": {
          "top": 4,
          "region": 2,
          "pre": 2,
          "bot": 1226
        }
      },
      "9": {
        "value": 2.7,
        "rank": {
          "top": 25,
          "region": 1,
          "pre": 1,
          "bot": 1199
        }
      },
      "10": {
        "value": 1.2,
        "rank": {
          "top": 112,
          "region": 8,
          "pre": 5,
          "bot": 1078
        }
      },
      "11": {
        "value": 0.2,
        "rank": {
          "top": 400,
          "region": 79,
          "pre": 13,
          "bot": 609
        }
      },
      "12": {
        "value": 0.2,
        "rank": {
          "top": 245,
          "region": 34,
          "pre": 7,
          "bot": 796
        }
      },
      "all": {
        "value": 16.6,
        "rank": {
          "top": 36,
          "region": 10,
          "pre": 4,
          "bot": 1194
        }
      }
    },
    "rain_70": {
      "1": {
        "value": 0.0,
        "rank": {
          "top": 1230,
          "region": 147,
          "pre": 23,
          "bot": 1
        }
      },
      "2": {
        "value": 0.0,
        "rank": {
          "top": 1230,
          "region": 147,
          "pre": 23,
          "bot": 1
        }
      },
      "3": {
        "value": 0.1,
        "rank": {
          "top": 176,
          "region": 38,
          "pre": 6,
          "bot": 870
        }
      },
      "4": {
        "value": 0.2,
        "rank": {
          "top": 241,
          "region": 75,
          "pre": 17,
          "bot": 888
        }
      },
      "5": {
        "value": 0.7,
        "rank": {
          "top": 76,
          "region": 24,
          "pre": 8,
          "bot": 1114
        }
      },
      "6": {
        "value": 2.3,
        "rank": {
          "top": 48,
          "region": 46,
          "pre": 12,
          "bot": 1178
        }
      },
      "7": {
        "value": 1.9,
        "rank": {
          "top": 37,
          "region": 25,
          "pre": 7,
          "bot": 1180
        }
      },
      "8": {
        "value": 2.2,
        "rank": {
          "top": 4,
          "region": 1,
          "pre": 1,
          "bot": 1226
        }
      },
      "9": {
        "value": 2.0,
        "rank": {
          "top": 14,
          "region": 1,
          "pre": 1,
          "bot": 1210
        }
      },
      "10": {
        "value": 0.7,
        "rank": {
          "top": 127,
          "region": 11,
          "pre": 8,
          "bot": 1045
        }
      },
      "11": {
        "value": 0.0,
        "rank": {
          "top": 1230,
          "region": 147,
          "pre": 23,
          "bot": 1
        }
      },
      "12": {
        "value": 0.1,
        "rank": {
          "top": 129,
          "region": 17,
          "pre": 6,
          "bot": 782
        }
      },
      "all": {
        "value": 10.1,
        "rank": {
          "top": 35,
          "region": 10,
          "pre": 4,
          "bot": 1196
        }
      }
    },
    "sm_rain": {
      "1": {
        "value": 70.9,
        "rank": {
          "top": 626,
          "region": 85,
          "pre": 12,
          "bot": 602
        }
      },
      "2": {
        "value": 104.1,
        "rank": {
          "top": 372,
          "region": 61,
          "pre": 12,
          "bot": 859
        }
      },
      "3": {
        "value": 166.3,
        "rank": {
          "top": 189,
          "region": 38,
          "pre": 8,
          "bot": 1041
        }
      },
      "4": {
        "value": 185.9,
        "rank": {
          "top": 154,
          "region": 57,
          "pre": 14,
          "bot": 1077
        }
      },
      "5": {
        "value": 237.9,
        "rank": {
          "top": 97,
          "region": 25,
          "pre": 8,
          "bot": 1133
        }
      },
      "6": {
        "value": 519.7,
        "rank": {
          "top": 49,
          "region": 46,
          "pre": 12,
          "bot": 1182
        }
      },
      "7": {
        "value": 479.5,
        "rank": {
          "top": 37,
          "region": 22,
          "pre": 6,
          "bot": 1194
        }
      },
      "8": {
        "value": 548.2,
        "rank": {
          "top": 5,
          "region": 2,
          "pre": 2,
          "bot": 1226
        }
      },
      "9": {
        "value": 534.2,
        "rank": {
          "top": 10,
          "region": 1,
          "pre": 1,
          "bot": 1221
        }
      },
      "10": {
        "value": 217.1,
        "rank": {
          "top": 173,
          "region": 10,
          "pre": 5,
          "bot": 1057
        }
      },
      "11": {
        "value": 91.1,
        "rank": {
          "top": 724,
          "region": 97,
          "pre": 19,
          "bot": 507
        }
      },
      "12": {
        "value": 74.1,
        "rank": {
          "top": 696,
          "region": 91,
          "pre": 15,
          "bot": 532
        }
      },
      "all": {
        "value": 3229.0,
        "rank": {
          "top": 33,
          "region": 10,
          "pre": 4,
          "bot": 1198
        }
      }
    },
    "sm_snowing": {
      "1": {},
      "2": {},
      "3": {},
      "4": {},
      "5": {},
      "6": {},
      "7": {},
      "8": {},
      "9": {},
      "10": {},
      "11": {},
      "12": {},
      "all": {}
    },
    "sm_sun": {
      "1": {
        "value": 180.2,
        "rank": {
          "top": 128,
          "region": 7,
          "pre": 6,
          "bot": 699
        }
      },
      "2": {
        "value": 164.6,
        "rank": {
          "top": 159,
          "region": 8,
          "pre": 6,
          "bot": 668
        }
      },
      "3": {
        "value": 182.6,
        "rank": {
          "top": 191,
          "region": 11,
          "pre": 6,
          "bot": 636
        }
      },
      "4": {
        "value": 187.3,
        "rank": {
          "top": 283,
          "region": 22,
          "pre": 5,
          "bot": 543
        }
      },
      "5": {
        "value": 181.4,
        "rank": {
          "top": 644,
          "region": 64,
          "pre": 5,
          "bot": 183
        }
      },
      "6": {
        "value": 110.9,
        "rank": {
          "top": 794,
          "region": 72,
          "pre": 9,
          "bot": 34
        }
      },
      "7": {
        "value": 160.6,
        "rank": {
          "top": 333,
          "region": 80,
          "pre": 11,
          "bot": 495
        }
      },
      "8": {
        "value": 166.1,
        "rank": {
          "top": 557,
          "region": 91,
          "pre": 12,
          "bot": 271
        }
      },
      "9": {
        "value": 135.8,
        "rank": {
          "top": 627,
          "region": 90,
          "pre": 12,
          "bot": 201
        }
      },
      "10": {
        "value": 163.0,
        "rank": {
          "top": 221,
          "region": 82,
          "pre": 11,
          "bot": 603
        }
      },
      "11": {
        "value": 158.5,
        "rank": {
          "top": 140,
          "region": 10,
          "pre": 7,
          "bot": 687
        }
      },
      "12": {
        "value": 172.3,
        "rank": {
          "top": 117,
          "region": 8,
          "pre": 6,
          "bot": 711
        }
      },
      "all": {
        "value": 1963.4,
        "rank": {
          "top": 229,
          "region": 30,
          "pre": 8,
          "bot": 599
        }
      }
    },
    "snowed_10": {
      "1": {},
      "2": {},
      "3": {},
      "4": {},
      "5": {},
      "6": {},
      "7": {},
      "8": {},
      "9": {},
      "10": {},
      "11": {},
      "12": {},
      "all": {}
    },
    "snowed_100": {
      "1": {},
      "2": {},
      "3": {},
      "4": {},
      "5": {},
      "6": {},
      "7": {},
      "8": {},
      "9": {},
      "10": {},
      "11": {},
      "12": {},
      "all": {}
    },
    "snowed_20": {
      "1": {},
      "2": {},
      "3": {},
      "4": {},
      "5": {},
      "6": {},
      "7": {},
      "8": {},
      "9": {},
      "10": {},
      "11": {},
      "12": {},
      "all": {}
    },
    "snowed_5": {
      "1": {},
      "2": {},
      "3": {},
      "4": {},
      "5": {},
      "6": {},
      "7": {},
      "8": {},
      "9": {},
      "10": {},
      "11": {},
      "12": {},
      "all": {}
    },
    "snowed_50": {
      "1": {},
      "2": {},
      "3": {},
      "4": {},
      "5": {},
      "6": {},
      "7": {},
      "8": {},
      "9": {},
      "10": {},
      "11": {},
      "12": {},
      "all": {}
    },
    "snowing_10": {
      "1": {},
      "2": {},
      "3": {},
      "4": {},
      "5": {},
      "6": {},
      "7": {},
      "8": {},
      "9": {},
      "10": {},
      "11": {},
      "12": {},
      "all": {}
    },
    "snowing_20": {
      "1": {},
      "2": {},
      "3": {},
      "4": {},
      "5": {},
      "6": {},
      "7": {},
      "8": {},
      "9": {},
      "10": {},
      "11": {},
      "12": {},
      "all": {}
    },
    "snowing_3": {
      "1": {},
      "2": {},
      "3": {},
      "4": {},
      "5": {},
      "6": {},
      "7": {},
      "8": {},
      "9": {},
      "10": {},
      "11": {},
      "12": {},
      "all": {}
    },
    "snowing_5": {
      "1": {},
      "2": {},
      "3": {},
      "4": {},
      "5": {},
      "6": {},
      "7": {},
      "8": {},
      "9": {},
      "10": {},
      "11": {},
      "12": {},
      "all": {}
    },
    "snowing_50": {
      "1": {},
      "2": {},
      "3": {},
      "4": {},
      "5": {},
      "6": {},
      "7": {},
      "8": {},
      "9": {},
      "10": {},
      "11": {},
      "12": {},
      "all": {}
    },
    "wind_10": {
      "1": {
        "value": 0.0,
        "rank": {
          "top": 874,
          "region": 116,
          "pre": 15,
          "bot": 1
        }
      },
      "2": {
        "value": 0.0,
        "rank": {
          "top": 874,
          "region": 116,
          "pre": 15,
          "bot": 1
        }
      },
      "3": {
        "value": 0.0,
        "rank": {
          "top": 874,
          "region": 116,
          "pre": 15,
          "bot": 1
        }
      },
      "4": {
        "value": 0.0,
        "rank": {
          "top": 874,
          "region": 116,
          "pre": 15,
          "bot": 1
        }
      },
      "5": {
        "value": 0.0,
        "rank": {
          "top": 874,
          "region": 116,
          "pre": 15,
          "bot": 1
        }
      },
      "6": {
        "value": 0.0,
        "rank": {
          "top": 874,
          "region": 116,
          "pre": 15,
          "bot": 1
        }
      },
      "7": {
        "value": 0.0,
        "rank": {
          "top": 874,
          "region": 116,
          "pre": 15,
          "bot": 1
        }
      },
      "8": {
        "value": 0.0,
        "rank": {
          "top": 874,
          "region": 116,
          "pre": 15,
          "bot": 1
        }
      },
      "9": {
        "value": 0.0,
        "rank": {
          "top": 874,
          "region": 116,
          "pre": 15,
          "bot": 1
        }
      },
      "10": {
        "value": 0.0,
        "rank": {
          "top": 874,
          "region": 116,
          "pre": 15,
          "bot": 1
        }
      },
      "11": {
        "value": 0.0,
        "rank": {
          "top": 874,
          "region": 116,
          "pre": 15,
          "bot": 1
        }
      },
      "12": {
        "value": 0.0,
        "rank": {
          "top": 874,
          "region": 116,
          "pre": 15,
          "bot": 1
        }
      },
      "all": {
        "value": 0.0,
        "rank": {
          "top": 874,
          "region": 116,
          "pre": 15,
          "bot": 1
        }
      }
    },
    "wind_15": {
      "1": {
        "value": 0.0,
        "rank": {
          "top": 874,
          "region": 116,
          "pre": 15,
          "bot": 1
        }
      },
      "2": {
        "value": 0.0,
        "rank": {
          "top": 874,
          "region": 116,
          "pre": 15,
          "bot": 1
        }
      },
      "3": {
        "value": 0.0,
        "rank": {
          "top": 874,
          "region": 116,
          "pre": 15,
          "bot": 1
        }
      },
      "4": {
        "value": 0.0,
        "rank": {
          "top": 874,
          "region": 116,
          "pre": 15,
          "bot": 1
        }
      },
      "5": {
        "value": 0.0,
        "rank": {
          "top": 874,
          "region": 116,
          "pre": 15,
          "bot": 1
        }
      },
      "6": {
        "value": 0.0,
        "rank": {
          "top": 874,
          "region": 116,
          "pre": 15,
          "bot": 1
        }
      },
      "7": {
        "value": 0.0,
        "rank": {
          "top": 874,
          "region": 116,
          "pre": 15,
          "bot": 1
        }
      },
      "8": {
        "value": 0.0,
        "rank": {
          "top": 874,
          "region": 116,
          "pre": 15,
          "bot": 1
        }
      },
      "9": {
        "value": 0.0,
        "rank": {
          "top": 874,
          "region": 116,
          "pre": 15,
          "bot": 1
        }
      },
      "10": {
        "value": 0.0,
        "rank": {
          "top": 874,
          "region": 116,
          "pre": 15,
          "bot": 1
        }
      },
      "11": {
        "value": 0.0,
        "rank": {
          "top": 874,
          "region": 116,
          "pre": 15,
          "bot": 1
        }
      },
      "12": {
        "value": 0.0,
        "rank": {
          "top": 874,
          "region": 116,
          "pre": 15,
          "bot": 1
        }
      },
      "all": {
        "value": 0.0,
        "rank": {
          "top": 874,
          "region": 116,
          "pre": 15,
          "bot": 1
        }
      }
    },
    "wind_20": {
      "1": {
        "value": 0.0,
        "rank": {
          "top": 874,
          "region": 116,
          "pre": 15,
          "bot": 1
        }
      },
      "2": {
        "value": 0.0,
        "rank": {
          "top": 874,
          "region": 116,
          "pre": 15,
          "bot": 1
        }
      },
      "3": {
        "value": 0.0,
        "rank": {
          "top": 874,
          "region": 116,
          "pre": 15,
          "bot": 1
        }
      },
      "4": {
        "value": 0.0,
        "rank": {
          "top": 874,
          "region": 116,
          "pre": 15,
          "bot": 1
        }
      },
      "5": {
        "value": 0.0,
        "rank": {
          "top": 874,
          "region": 116,
          "pre": 15,
          "bot": 1
        }
      },
      "6": {
        "value": 0.0,
        "rank": {
          "top": 874,
          "region": 116,
          "pre": 15,
          "bot": 1
        }
      },
      "7": {
        "value": 0.0,
        "rank": {
          "top": 874,
          "region": 116,
          "pre": 15,
          "bot": 1
        }
      },
      "8": {
        "value": 0.0,
        "rank": {
          "top": 874,
          "region": 116,
          "pre": 15,
          "bot": 1
        }
      },
      "9": {
        "value": 0.0,
        "rank": {
          "top": 874,
          "region": 116,
          "pre": 15,
          "bot": 1
        }
      },
      "10": {
        "value": 0.0,
        "rank": {
          "top": 874,
          "region": 116,
          "pre": 15,
          "bot": 1
        }
      },
      "11": {
        "value": 0.0,
        "rank": {
          "top": 874,
          "region": 116,
          "pre": 15,
          "bot": 1
        }
      },
      "12": {
        "value": 0.0,
        "rank": {
          "top": 874,
          "region": 116,
          "pre": 15,
          "bot": 1
        }
      },
      "all": {
        "value": 0.0,
        "rank": {
          "top": 874,
          "region": 116,
          "pre": 15,
          "bot": 1
        }
      }
    },
    "wind_30": {
      "1": {
        "value": 0.0,
        "rank": {
          "top": 874,
          "region": 116,
          "pre": 15,
          "bot": 1
        }
      },
      "2": {
        "value": 0.0,
        "rank": {
          "top": 874,
          "region": 116,
          "pre": 15,
          "bot": 1
        }
      },
      "3": {
        "value": 0.0,
        "rank": {
          "top": 874,
          "region": 116,
          "pre": 15,
          "bot": 1
        }
      },
      "4": {
        "value": 0.0,
        "rank": {
          "top": 874,
          "region": 116,
          "pre": 15,
          "bot": 1
        }
      },
      "5": {
        "value": 0.0,
        "rank": {
          "top": 874,
          "region": 116,
          "pre": 15,
          "bot": 1
        }
      },
      "6": {
        "value": 0.0,
        "rank": {
          "top": 874,
          "region": 116,
          "pre": 15,
          "bot": 1
        }
      },
      "7": {
        "value": 0.0,
        "rank": {
          "top": 874,
          "region": 116,
          "pre": 15,
          "bot": 1
        }
      },
      "8": {
        "value": 0.0,
        "rank": {
          "top": 874,
          "region": 116,
          "pre": 15,
          "bot": 1
        }
      },
      "9": {
        "value": 0.0,
        "rank": {
          "top": 874,
          "region": 116,
          "pre": 15,
          "bot": 1
        }
      },
      "10": {
        "value": 0.0,
        "rank": {
          "top": 874,
          "region": 116,
          "pre": 15,
          "bot": 1
        }
      },
      "11": {
        "value": 0.0,
        "rank": {
          "top": 874,
          "region": 116,
          "pre": 15,
          "bot": 1
        }
      },
      "12": {
        "value": 0.0,
        "rank": {
          "top": 874,
          "region": 116,
          "pre": 15,
          "bot": 1
        }
      },
      "all": {
        "value": 0.0,
        "rank": {
          "top": 874,
          "region": 116,
          "pre": 15,
          "bot": 1
        }
      }
    }
  },
  "meteo": {
    "11016": {
      "station_name": "稚内",
      "official_name": "稚内地方気象台"
    },
    "12442": {
      "station_name": "旭川",
      "official_name": "旭川地方気象台"
    },
    "14163": {
      "station_name": "札幌",
      "official_name": "札幌管区気象台"
    },
    "17341": {
      "station_name": "網走",
      "official_name": "網走地方気象台"
    },
    "19432": {
      "station_name": "釧路",
      "official_name": "釧路地方気象台"
    },
    "21323": {
      "station_name": "室蘭",
      "official_name": "室蘭地方気象台"
    },
    "23232": {
      "station_name": "函館",
      "official_name": "函館地方気象台"
    },
    "31312": {
      "station_name": "青森",
      "official_name": "青森地方気象台"
    },
    "32402": {
      "station_name": "秋田",
      "official_name": "秋田地方気象台"
    },
    "33431": {
      "station_name": "盛岡",
      "official_name": "盛岡地方気象台"
    },
    "34392": {
      "station_name": "仙台",
      "official_name": "仙台管区気象台"
    },
    "35426": {
      "station_name": "山形",
      "official_name": "山形地方気象台"
    },
    "36127": {
      "station_name": "福島",
      "official_name": "福島地方気象台"
    },
    "40201": {
      "station_name": "水戸",
      "official_name": "水戸地方気象台"
    },
    "40336": {
      "station_name": "つくば",
      "official_name": "高層気象台"
    },
    "41277": {
      "station_name": "宇都宮",
      "official_name": "宇都宮地方気象台"
    },
    "42251": {
      "station_name": "前橋",
      "official_name": "前橋地方気象台"
    },
    "43056": {
      "station_name": "熊谷",
      "official_name": "熊谷地方気象台"
    },
    "44132": {
      "station_name": "東京",
      "official_name": "東京管区気象台"
    },
    "45148": {
      "station_name": "銚子",
      "official_name": "銚子地方気象台"
    },
    "46106": {
      "station_name": "横浜",
      "official_name": "横浜地方気象台"
    },
    "48156": {
      "station_name": "長野",
      "official_name": "長野地方気象台"
    },
    "49142": {
      "station_name": "甲府",
      "official_name": "甲府地方気象台"
    },
    "50331": {
      "station_name": "静岡",
      "official_name": "静岡地方気象台"
    },
    "51106": {
      "station_name": "名古屋",
      "official_name": "名古屋地方気象台"
    },
    "52586": {
      "station_name": "岐阜",
      "official_name": "岐阜地方気象台"
    },
    "53133": {
      "station_name": "津",
      "official_name": "津地方気象台"
    },
    "54232": {
      "station_name": "新潟",
      "official_name": "新潟地方気象台"
    },
    "55102": {
      "station_name": "富山",
      "official_name": "富山地方気象台"
    },
    "56227": {
      "station_name": "金沢",
      "official_name": "金沢地方気象台"
    },
    "57066": {
      "station_name": "福井",
      "official_name": "福井地方気象台"
    },
    "60131": {
      "station_name": "彦根",
      "official_name": "彦根地方気象台"
    },
    "61286": {
      "station_name": "京都",
      "official_name": "京都地方気象台"
    },
    "62078": {
      "station_name": "大阪",
      "official_name": "大阪管区気象台"
    },
    "63518": {
      "station_name": "神戸",
      "official_name": "神戸地方気象台"
    },
    "64036": {
      "station_name": "奈良",
      "official_name": "奈良地方気象台"
    },
    "65042": {
      "station_name": "和歌山",
      "official_name": "和歌山地方気象台"
    },
    "66408": {
      "station_name": "岡山",
      "official_name": "岡山地方気象台"
    },
    "67437": {
      "station_name": "広島",
      "official_name": "広島地方気象台"
    },
    "68132": {
      "station_name": "松江",
      "official_name": "松江地方気象台"
    },
    "69122": {
      "station_name": "鳥取",
      "official_name": "鳥取地方気象台"
    },
    "71106": {
      "station_name": "徳島",
      "official_name": "徳島地方気象台"
    },
    "72086": {
      "station_name": "高松",
      "official_name": "高松地方気象台"
    },
    "73166": {
      "station_name": "松山",
      "official_name": "松山地方気象台"
    },
    "74182": {
      "station_name": "高知",
      "official_name": "高知地方気象台"
    },
    "81428": {
      "station_name": "下関",
      "official_name": "下関地方気象台"
    },
    "82182": {
      "station_name": "福岡",
      "official_name": "福岡管区気象台"
    },
    "83216": {
      "station_name": "大分",
      "official_name": "大分地方気象台"
    },
    "84496": {
      "station_name": "長崎",
      "official_name": "長崎地方気象台"
    },
    "85142": {
      "station_name": "佐賀",
      "official_name": "佐賀地方気象台"
    },
    "86141": {
      "station_name": "熊本",
      "official_name": "熊本地方気象台"
    },
    "87376": {
      "station_name": "宮崎",
      "official_name": "宮崎地方気象台"
    },
    "88317": {
      "station_name": "鹿児島",
      "official_name": "鹿児島地方気象台"
    },
    "91197": {
      "station_name": "那覇",
      "official_name": "沖縄気象台"
    },
    "92011": {
      "station_name": "南大東",
      "official_name": "南大東島地方気象台"
    },
    "93041": {
      "station_name": "宮古島",
      "official_name": "宮古島地方気象台"
    },
    "94081": {
      "station_name": "石垣島",
      "official_name": "石垣島地方気象台"
    }
  },
  "same_pre": {
    "87041": {
      "station_name": "高千穂",
      "official_name": "高千穂アメダス"
    },
    "87066": {
      "station_name": "古江",
      "official_name": "古江アメダス"
    },
    "87071": {
      "station_name": "鞍岡",
      "official_name": "鞍岡アメダス"
    },
    "87086": {
      "station_name": "日之影",
      "official_name": "日之影アメダス"
    },
    "87127": {
      "station_name": "諸塚",
      "official_name": "諸塚アメダス"
    },
    "87136": {
      "station_name": "北方",
      "official_name": "北方アメダス"
    },
    "87141": {
      "station_name": "延岡",
      "official_name": "延岡特別地域気象観測所"
    },
    "87157": {
      "station_name": "椎葉",
      "official_name": "椎葉アメダス"
    },
    "87181": {
      "station_name": "日向",
      "official_name": "日向アメダス"
    },
    "87206": {
      "station_name": "神門",
      "official_name": "神門アメダス"
    },
    "87231": {
      "station_name": "西米良",
      "official_name": "西米良アメダス"
    },
    "87251": {
      "station_name": "都農",
      "official_name": "都農アメダス"
    },
    "87301": {
      "station_name": "加久藤",
      "official_name": "加久藤アメダス"
    },
    "87331": {
      "station_name": "西都",
      "official_name": "西都アメダス"
    },
    "87346": {
      "station_name": "えびの高原",
      "official_name": "えびの高原アメダス"
    },
    "87352": {
      "station_name": "小林",
      "official_name": "小林アメダス"
    },
    "87371": {
      "station_name": "国富",
      "official_name": "国富アメダス"
    },
    "87376": {
      "station_name": "宮崎",
      "official_name": "宮崎地方気象台"
    },
    "87412": {
      "station_name": "赤江",
      "official_name": "宮崎航空気象観測所"
    },
    "87426": {
      "station_name": "都城",
      "official_name": "都城特別地域気象観測所"
    },
    "87461": {
      "station_name": "酒谷",
      "official_name": "酒谷アメダス"
    },
    "87492": {
      "station_name": "油津",
      "official_name": "油津特別地域気象観測所"
    },
    "87501": {
      "station_name": "串間",
      "official_name": "串間アメダス"
    }
  },
  "similar_all": {
    "71251": {
      "similar": 0.887,
      "station_name": "木頭",
      "pref": "徳島県",
      "city": "那賀郡那賀町",
      "official_name": "木頭アメダス"
    },
    "74071": {
      "similar": 0.869,
      "station_name": "本山",
      "pref": "高知県",
      "city": "長岡郡本山町",
      "official_name": "本山アメダス"
    },
    "87231": {
      "similar": 0.868,
      "station_name": "西米良",
      "pref": "宮崎県",
      "city": "児湯郡西米良村",
      "official_name": "西米良アメダス"
    },
    "64206": {
      "similar": 0.861,
      "station_name": "上北山",
      "pref": "奈良県",
      "city": "吉野郡上北山村",
      "official_name": "上北山アメダス"
    },
    "74361": {
      "similar": 0.856,
      "station_name": "窪川",
      "pref": "高知県",
      "city": "高岡郡四万十町",
      "official_name": "窪川アメダス"
    }
  },
  "similar_meteo": {
    "74182": {
      "similar": 0.761,
      "station_name": "高知",
      "pref": "高知県",
      "city": "高知市",
      "official_name": "高知地方気象台"
    },
    "87376": {
      "similar": 0.754,
      "station_name": "宮崎",
      "pref": "宮崎県",
      "city": "宮崎市",
      "official_name": "宮崎地方気象台"
    },
    "50331": {
      "similar": 0.683,
      "station_name": "静岡",
      "pref": "静岡県",
      "city": "静岡市",
      "official_name": "静岡地方気象台"
    },
    "85142": {
      "similar": 0.678,
      "station_name": "佐賀",
      "pref": "佐賀県",
      "city": "佐賀市",
      "official_name": "佐賀地方気象台"
    },
    "41277": {
      "similar": 0.664,
      "station_name": "宇都宮",
      "pref": "栃木県",
      "city": "宇都宮市",
      "official_name": "宇都宮地方気象台"
    }
  }
}