{
  "81011": {
    "value": 3.7,
    "rank": 1
  },
  "81071": {
    "value": 3.2,
    "rank": 3
  },
  "81116": {
    "value": 3.2,
    "rank": 3
  },
  "81151": {
    "value": 3.5,
    "rank": 2
  },
  "81167": {
    "value": 3.1,
    "rank": 6
  },
  "81196": {
    "value": 2.9,
    "rank": 9
  },
  "81228": {
    "value": 2.6,
    "rank": 15
  },
  "81231": {
    "value": 3.2,
    "rank": 3
  },
  "81266": {
    "value": 2.9,
    "rank": 9
  },
  "81271": {
    "value": 2.5,
    "rank": 17
  },
  "81286": {
    "value": 2.5,
    "rank": 17
  },
  "81301": {
    "value": 3.1,
    "rank": 6
  },
  "81321": {
    "value": 2.7,
    "rank": 13
  },
  "81371": {
    "value": 2.3,
    "rank": 20
  },
  "81386": {
    "value": 2.6,
    "rank": 15
  },
  "81397": {
    "value": 2.8,
    "rank": 12
  },
  "81428": {
    "value": 3,
    "rank": 8
  },
  "81436": {
    "value": 2.5,
    "rank": 17
  },
  "81481": {
    "value": 2.7,
    "rank": 13
  },
  "81486": {
    "value": 2.9,
    "rank": 9
  }
}