{
  "33006": {
    "value": 156.3,
    "rank": 2
  },
  "33026": {
    "value": 125.5,
    "rank": 14
  },
  "33071": {
    "value": 117.6,
    "rank": 18
  },
  "33136": {
    "value": 131.4,
    "rank": 12
  },
  "33146": {
    "value": 150,
    "rank": 4
  },
  "33166": {
    "value": 100.2,
    "rank": 28
  },
  "33176": {
    "value": 106.7,
    "rank": 24
  },
  "33186": {
    "value": 82.4,
    "rank": 32
  },
  "33206": {
    "value": 151.2,
    "rank": 3
  },
  "33226": {
    "value": 102.6,
    "rank": 26
  },
  "33296": {
    "value": 110.5,
    "rank": 21
  },
  "33326": {
    "value": 133.6,
    "rank": 11
  },
  "33336": {
    "value": 148.5,
    "rank": 5
  },
  "33371": {
    "value": 94.9,
    "rank": 30
  },
  "33421": {
    "value": 102,
    "rank": 27
  },
  "33431": {
    "value": 117.7,
    "rank": 17
  },
  "33441": {
    "value": 100,
    "rank": 29
  },
  "33472": {
    "value": 146.8,
    "rank": 6
  },
  "33501": {
    "value": 117.1,
    "rank": 19
  },
  "33526": {
    "value": 127,
    "rank": 13
  },
  "33581": {
    "value": 105.1,
    "rank": 25
  },
  "33616": {
    "value": 157.6,
    "rank": 1
  },
  "33631": {
    "value": 84.6,
    "rank": 31
  },
  "33671": {
    "value": 117.8,
    "rank": 16
  },
  "33716": {
    "value": 108.2,
    "rank": 23
  },
  "33751": {
    "value": 142.1,
    "rank": 7
  },
  "33776": {
    "value": 109.7,
    "rank": 22
  },
  "33781": {
    "value": 113.5,
    "rank": 20
  },
  "33801": {
    "value": 138.3,
    "rank": 8
  },
  "33877": {
    "value": 137.9,
    "rank": 9
  },
  "33911": {
    "value": 125.5,
    "rank": 14
  },
  "33921": {
    "value": 135.6,
    "rank": 10
  }
}