{
  "91021": {
    "value": 0.1,
    "rank": 2
  },
  "91066": {
    "value": 0.1,
    "rank": 2
  },
  "91096": {
    "value": 0.1,
    "rank": 2
  },
  "91107": {
    "value": 0.1,
    "rank": 2
  },
  "91121": {
    "value": 0.1,
    "rank": 2
  },
  "91141": {
    "value": 0.1,
    "rank": 2
  },
  "91146": {
    "value": 0.2,
    "rank": 1
  },
  "91161": {
    "value": 0.1,
    "rank": 2
  },
  "91166": {
    "value": 0.1,
    "rank": 2
  },
  "91181": {
    "value": 0.1,
    "rank": 2
  },
  "91236": {
    "value": 0.1,
    "rank": 2
  }
}